{
  "title": {
    "en_us": "Harle  Episode 1  The First Trap",
    "ja_jp": "ハール 第1話 はじまりの罠",
    "zh_cn": "哈尔 第1话 最初的陷阱",
    "zh_tw": "哈魯 第1話 最初的圈套"
  },
  "outline": {
    "title": {
      "en_us": "",
      "ja_jp": "",
      "zh_cn": "",
      "zh_tw": ""
    },
    "content": {
      "en_us": "Skip this scene?",
      "ja_jp": "このストーリーをスキップしますか？",
      "zh_cn": "要跳过此剧情吗？",
      "zh_tw": "請確認是否略過劇情？"
    }
  },
  "prev": "",
  "next": "100019022",
  "content": [
    {
      "icon": "",
      "name": {
        "en_us": "SYS",
        "ja_jp": "SYS",
        "zh_cn": "SYS",
        "zh_tw": "SYS"
      },
      "context": {
        "en_us": "The Officers Academy: a training ground for those\\nwho would one day serve the Alberian royal family.\\nI longed for knighthood, knowing it would deliver\\nme from the bottom rung of society I was born into.\\nUpon enrolling, my acumen was quickly noted.",
        "ja_jp": "アルベリア<ruby><rb>王家</rb><rt>おうけ</rt></ruby><ruby><rb>直属</rb><rt>ちょくぞく</rt></ruby>の<ruby><rb>騎士</rb><rt>きし</rt></ruby>を<ruby><rb>育</rb><rt>そだ</rt></ruby>てる<ruby><rb>学校</rb><rt>がっこう</rt></ruby>\\n<ruby><rb>将士</rb><rt>しょうし</rt></ruby><ruby><rb>学校</rb><rt>がっこう</rt></ruby>――\\n<ruby><rb>社会</rb><rt>しゃかい</rt></ruby>の<ruby><rb>底辺</rb><rt>ていへん</rt></ruby>から<ruby><rb>脱</rb><rt>だっ</rt></ruby>するために\\n<ruby><rb>私</rb><rt>わたし</rt></ruby>は<ruby><rb>騎士</rb><rt>きし</rt></ruby>の<ruby><rb>世界</rb><rt>せかい</rt></ruby>に<ruby><rb>足</rb><rt>あし</rt></ruby>を<ruby><rb>踏</rb><rt>ふ</rt></ruby>み<ruby><rb>入</rb><rt>い</rt></ruby>れた。\\n<ruby><rb>私</rb><rt>わたし</rt></ruby>は<ruby><rb>周囲</rb><rt>しゅうい</rt></ruby>も<ruby><rb>認</rb><rt>みと</rt></ruby>める<ruby><rb>成績</rb><rt>せいせき</rt></ruby>を<ruby><rb>修</rb><rt>おさ</rt></ruby>めた。",
        "zh_cn": "军事学校——\\n培养阿尔贝里亚王室直属骑士的学校。\\n为了脱离社会底层，\\n我选择了当一名骑士，\\n而我的优秀成绩也得到了周围的认可。",
        "zh_tw": "培育阿爾貝利亞王家直屬騎士的學校，\\n軍官學校──\\n為了擺脫社會底層，\\n於是我踏進騎士的世界，\\n並取得周遭人們皆認可的成績。"
      },
      "voice": "",
      "book": ""
    },
    {
      "icon": "",
      "name": {
        "en_us": "SYS",
        "ja_jp": "SYS",
        "zh_cn": "SYS",
        "zh_tw": "SYS"
      },
      "context": {
        "en_us": "I never doubted for a second that I was on the path\\ntoward accomplishing my dream. I swore I would\\nuse my platform to create a world where every\\nhuman being would be treated equally, regardless\\nof their birth or social standing.",
        "ja_jp": "これで<ruby><rb>理想</rb><rt>りそう</rt></ruby>に<ruby><rb>近</rb><rt>ちか</rt></ruby>づけると<ruby><rb>疑</rb><rt>うたが</rt></ruby>わなかった。\\n<ruby><rb>必</rb><rt>かなら</rt></ruby>ず<ruby><rb>出世</rb><rt>しゅっせ</rt></ruby>して、すべての<ruby><rb>人間</rb><rt>にんげん</rt></ruby>が\\n<ruby><rb>生</rb><rt>う</rt></ruby>まれや<ruby><rb>身分</rb><rt>みぶん</rt></ruby>を<ruby><rb>問</rb><rt>と</rt></ruby>われずに\\n<ruby><rb>平等</rb><rt>びょうどう</rt></ruby>に<ruby><rb>評価</rb><rt>ひょうか</rt></ruby>される<ruby><rb>世界</rb><rt>せかい</rt></ruby>を<ruby><rb>作</rb><rt>つく</rt></ruby>るのだと\\n<ruby><rb>心</rb><rt>こころ</rt></ruby>に<ruby><rb>誓</rb><rt>ちか</rt></ruby>っていた。",
        "zh_cn": "我坚信这样便可以接近我的理想。\\n我在心里暗自发誓，\\n一定要出人头地，\\n创造一个所有人不论身份地位，\\n都能得到公正评价的世界。",
        "zh_tw": "我深信這樣就能接近理想，\\n並在心中暗自發誓──\\n我絕對會出人頭地，\\n然後創造一個不問出生與身分，\\n所有人都能平等獲得評價的世界。"
      },
      "voice": "",
      "book": ""
    },
    {
      "icon": "",
      "name": {
        "en_us": "SYS",
        "ja_jp": "SYS",
        "zh_cn": "SYS",
        "zh_tw": "SYS"
      },
      "context": {
        "en_us": "But all that awaited me was the bitter sting of\\nreality. Leif and Cecile, both of noble birth,\\nreceived stations within the Royal Guard.\\nMeanwhile, I—a commoner—was doomed to\\nbecome part of the worthless Capital Guard.",
        "ja_jp": "しかし、<ruby><rb>待</rb><rt>ま</rt></ruby>っていたのは<ruby><rb>無慈悲</rb><rt>むじひ</rt></ruby>な<ruby><rb>現実</rb><rt>げんじつ</rt></ruby>。\\n<ruby><rb>名門</rb><rt>めいもん</rt></ruby><ruby><rb>貴族</rb><rt>きぞく</rt></ruby>の<ruby><rb>出</rb><rt>で</rt></ruby>であるリーフとセシルは\\n<ruby><rb>近衛騎士</rb><rt>このえきし</rt></ruby>に<ruby><rb>登用</rb><rt>とうよう</rt></ruby>され、\\n<ruby><rb>平民</rb><rt>へいみん</rt></ruby>の<ruby><rb>私</rb><rt>わたし</rt></ruby>はしがない<ruby><rb>王都</rb><rt>おうと</rt></ruby><ruby><rb>守備</rb><rt>しゅび</rt></ruby><ruby><rb>隊</rb><rt>たい</rt></ruby>に\\n<ruby><rb>配属</rb><rt>はいぞく</rt></ruby>されることとなったのだった。",
        "zh_cn": "然而，等待我的却是残酷的现实。\\n出身名门贵族的利弗和赛希尔\\n被录用为近卫骑士，\\n而平民出身的我则被分配到了\\n不起眼的王都守卫队。",
        "zh_tw": "然而，等著我的卻是殘酷的現實。\\n名門貴族出身的李弗與賽席爾\\n被選為近衛騎士，\\n而身為平民的我卻被分配到\\n不值一提的王都守衛隊。"
      },
      "voice": "",
      "book": ""
    },
    {
      "icon": "",
      "name": {
        "en_us": "SYS",
        "ja_jp": "SYS",
        "zh_cn": "SYS",
        "zh_tw": "SYS"
      },
      "context": {
        "en_us": "Three years later...",
        "ja_jp": "それから3<ruby><rb>年</rb><rt>ねん</rt></ruby><ruby><rb>後</rb><rt>ご</rt></ruby>――",
        "zh_cn": "3年后——",
        "zh_tw": "在那之後過了三年──"
      },
      "voice": "",
      "book": ""
    },
    {
      "icon": "120010_01",
      "name": {
        "en_us": "Minister",
        "ja_jp": "大臣",
        "zh_cn": "大臣",
        "zh_tw": "大臣"
      },
      "context": {
        "en_us": "Harle, I hereby appoint you\\nchief of the Capital Guard.",
        "ja_jp": "ハール、<ruby><rb>貴公</rb><rt>きこう</rt></ruby>を<ruby><rb>王都</rb><rt>おうと</rt></ruby><ruby><rb>守備</rb><rt>しゅび</rt></ruby><ruby><rb>隊</rb><rt>たい</rt></ruby>の\\n<ruby><rb>隊長</rb><rt>たいちょう</rt></ruby>に<ruby><rb>任命</rb><rt>にんめい</rt></ruby>する。",
        "zh_cn": "哈尔，现任命你为\\n王都守卫队队长。",
        "zh_tw": "哈魯，在此任命你為\\n王都守衛隊的隊長。"
      },
      "voice": "",
      "book": ""
    },
    {
      "icon": "100019_02",
      "name": {
        "en_us": "Harle",
        "ja_jp": "ハール",
        "zh_cn": "哈尔",
        "zh_tw": "哈魯"
      },
      "context": {
        "en_us": "...I humbly and gratefully accept.",
        "ja_jp": "……ありがたき<ruby><rb>幸</rb><rt>しあわ</rt></ruby>せ。",
        "zh_cn": "感激不尽……",
        "zh_tw": "……榮幸之至。"
      },
      "voice": "",
      "book": ""
    },
    {
      "icon": "100019_02",
      "name": {
        "en_us": "Harle",
        "ja_jp": "ハール",
        "zh_cn": "哈尔",
        "zh_tw": "哈魯"
      },
      "context": {
        "en_us": "(Pitiful that this is the highest station a\\ncommoner could ever hope to reach.)",
        "ja_jp": "（『<ruby><rb>王都</rb><rt>おうと</rt></ruby><ruby><rb>守備</rb><rt>しゅび</rt></ruby><ruby><rb>隊</rb><rt>たい</rt></ruby>』の<ruby><rb>隊長</rb><rt>たいちょう</rt></ruby>……。これが\\n　<ruby><rb>平民</rb><rt>へいみん</rt></ruby>の<ruby><rb>限界</rb><rt>げんかい</rt></ruby>ということですか）",
        "zh_cn": "（平民最多也只能当个\\n“王都守卫队”的队长吗……）",
        "zh_tw": "（「王都守衛隊」的隊長……\\n這就是所謂平民的極限嗎。）"
      },
      "voice": "",
      "book": ""
    },
    {
      "icon": "100019_02",
      "name": {
        "en_us": "Harle",
        "ja_jp": "ハール",
        "zh_cn": "哈尔",
        "zh_tw": "哈魯"
      },
      "context": {
        "en_us": "(There's no future for a country that values\\nsocial standing above all. I must enact my\\nplan.)",
        "ja_jp": "（くだらない<ruby><rb>身分主義</rb><rt>みぶんしゅぎ</rt></ruby>のこの<ruby><rb>国</rb><rt>くに</rt></ruby>に\\n　<ruby><rb>未来</rb><rt>みらい</rt></ruby>はない。<ruby><rb>私</rb><rt>わたし</rt></ruby>は<ruby><rb>私</rb><rt>わたし</rt></ruby>の<ruby><rb>計画</rb><rt>けいかく</rt></ruby>を――）",
        "zh_cn": "（这个一味看重出身的\\n国家没有未来。\\n我要实行自己的计划——）",
        "zh_tw": "（這個執著於\\n愚蠢身分主義的國家沒有未來。\\n我有我自己的計畫──）"
      },
      "voice": "",
      "book": ""
    },
    {
      "icon": "100019_02",
      "name": {
        "en_us": "???",
        "ja_jp": "？？？",
        "zh_cn": "？？？",
        "zh_tw": "？？？"
      },
      "context": {
        "en_us": "Congratulations on your promotion.",
        "ja_jp": "<ruby><rb>昇進</rb><rt>しょうしん</rt></ruby>、おめでとうございます。",
        "zh_cn": "恭喜你升职。",
        "zh_tw": "恭喜你升遷。"
      },
      "voice": "",
      "book": ""
    },
    {
      "icon": "100014_02",
      "name": {
        "en_us": "Phares",
        "ja_jp": "ファルエス",
        "zh_cn": "法尔艾斯",
        "zh_tw": "法魯艾斯"
      },
      "context": {
        "en_us": "But I must say, I question my father's\\nlogic in appointing you as such.",
        "ja_jp": "ですが、<ruby><rb>父上</rb><rt>ちちうえ</rt></ruby>ももったいない\\n<ruby><rb>采配</rb><rt>さいはい</rt></ruby>をなさる。",
        "zh_cn": "不过，父王真是大材小用。",
        "zh_tw": "不過，父王這項決策還真是浪費呢。"
      },
      "voice": "",
      "book": ""
    },
    {
      "icon": "100014_02",
      "name": {
        "en_us": "Phares",
        "ja_jp": "ファルエス",
        "zh_cn": "法尔艾斯",
        "zh_tw": "法魯艾斯"
      },
      "context": {
        "en_us": "A knight of your skill is far more suited\\nto a position within the Royal Guard.",
        "ja_jp": "あなたほどの<ruby><rb>騎士</rb><rt>きし</rt></ruby>ならば、\\n<ruby><rb>近衛騎士</rb><rt>このえきし</rt></ruby>にふさわしいでしょうに。",
        "zh_cn": "像你这般优秀的骑士，\\n应该当近卫骑士才是 。",
        "zh_tw": "像你這樣的騎士，\\n明明更適合擔任近衛騎士。"
      },
      "voice": "",
      "book": ""
    },
    {
      "icon": "100019_02",
      "name": {
        "en_us": "Harle",
        "ja_jp": "ハール",
        "zh_cn": "哈尔",
        "zh_tw": "哈魯"
      },
      "context": {
        "en_us": "Why, Prince Phares. I am honored that\\nyou would think so. Truly, you give me\\ntoo much credit.",
        "ja_jp": "これはこれは、ファルエス<ruby><rb>殿下</rb><rt>でんか</rt></ruby>。\\nお<ruby><rb>気持</rb><rt>きも</rt></ruby>ちはありがたいですが、\\n<ruby><rb>買</rb><rt>か</rt></ruby>い<ruby><rb>被</rb><rt>かぶ</rt></ruby>りすぎです。",
        "zh_cn": "这不是法尔艾斯殿下吗。\\n很感激您的赏识，\\n但您未免过于抬举我了。",
        "zh_tw": "原來是法魯艾斯殿下。\\n非常感謝您的讚美，\\n您太過獎了。"
      },
      "voice": "",
      "book": ""
    },
    {
      "icon": "100014_02",
      "name": {
        "en_us": "Phares",
        "ja_jp": "ファルエス",
        "zh_cn": "法尔艾斯",
        "zh_tw": "法魯艾斯"
      },
      "context": {
        "en_us": "I only speak the truth. In fact, it is for\\nthat reason I have come to you today.",
        "ja_jp": "おや、<ruby><rb>私</rb><rt>わたし</rt></ruby>は<ruby><rb>真実</rb><rt>しんじつ</rt></ruby>を<ruby><rb>言</rb><rt>い</rt></ruby>っただけですよ。\\nだからこそ、<ruby><rb>私</rb><rt>わたし</rt></ruby>はここに<ruby><rb>来</rb><rt>き</rt></ruby>たのです。",
        "zh_cn": "哪里，我只是实话实说。\\n我来这里，也是为了此事。",
        "zh_tw": "喔？我只不過說出事實而已。\\n況且我也是因此才來到這裡的。"
      },
      "voice": "",
      "book": ""
    },
    {
      "icon": "100014_02",
      "name": {
        "en_us": "Phares",
        "ja_jp": "ファルエス",
        "zh_cn": "法尔艾斯",
        "zh_tw": "法魯艾斯"
      },
      "context": {
        "en_us": "Harle, I would like you to serve\\nas my personal guard.",
        "ja_jp": "ハール、あなたさえよければ\\n<ruby><rb>私付</rb><rt>わたしづ</rt></ruby>きの<ruby><rb>近衛騎士</rb><rt>このえきし</rt></ruby>になりませんか？",
        "zh_cn": "哈尔，你愿意的话，\\n当我专属的近卫骑士如何？",
        "zh_tw": "哈魯，如果你願意，\\n要不要成為我的貼身近衛騎士呢？"
      },
      "voice": "",
      "book": ""
    },
    {
      "icon": "100014_02",
      "name": {
        "en_us": "Phares",
        "ja_jp": "ファルエス",
        "zh_cn": "法尔艾斯",
        "zh_tw": "法魯艾斯"
      },
      "context": {
        "en_us": "Given your other recent appointment,\\nit may be quite the endeavor to take\\nboth positions at once—this I recognize.",
        "ja_jp": "<ruby><rb>王都</rb><rt>おうと</rt></ruby><ruby><rb>守備</rb><rt>しゅび</rt></ruby><ruby><rb>隊</rb><rt>たい</rt></ruby>の<ruby><rb>隊長</rb><rt>たいちょう</rt></ruby>に<ruby><rb>任</rb><rt>にん</rt></ruby>じられた<ruby><rb>直後</rb><rt>ちょくご</rt></ruby>\\nですし、しばらくは<ruby><rb>兼任</rb><rt>けんにん</rt></ruby>という<ruby><rb>形</rb><rt>かたち</rt></ruby>で\\n<ruby><rb>激務</rb><rt>げきむ</rt></ruby>にはなりますが……。",
        "zh_cn": "不过你刚被任命为王都守卫队队长，\\n要辛苦你暂时兼顾两边，\\n职务会变得繁重……",
        "zh_tw": "但因為你剛被任命為王都守衛隊隊長，\\n所以暫時須要你身兼二職，\\n會相當辛苦就是……"
      },
      "voice": "",
      "book": ""
    },
    {
      "icon": "100019_02",
      "name": {
        "en_us": "Harle",
        "ja_jp": "ハール",
        "zh_cn": "哈尔",
        "zh_tw": "哈魯"
      },
      "context": {
        "en_us": "I am most humbled by your words.\\nIf I may ask, what moved you to\\napproach a man of my lowly caliber?",
        "ja_jp": "<ruby><rb>嬉</rb><rt>うれ</rt></ruby>しいお<ruby><rb>話</rb><rt>はなし</rt></ruby>ではありますが、\\nどうして<ruby><rb>私</rb><rt>わたし</rt></ruby>のような<ruby><rb>者</rb><rt>もの</rt></ruby>を？",
        "zh_cn": "不胜荣幸，\\n但为什么是我呢？",
        "zh_tw": "雖然是非常令人高興的提議，\\n不過為何會選上我呢？"
      },
      "voice": "",
      "book": ""
    },
    {
      "icon": "100014_02",
      "name": {
        "en_us": "Phares",
        "ja_jp": "ファルエス",
        "zh_cn": "法尔艾斯",
        "zh_tw": "法魯艾斯"
      },
      "context": {
        "en_us": "Because I believe only you can\\nlive up to my expectations.\\nDo you accept my offer?",
        "ja_jp": "あなたならば<ruby><rb>私</rb><rt>わたし</rt></ruby>の<ruby><rb>期待</rb><rt>きたい</rt></ruby>に<ruby><rb>応</rb><rt>こた</rt></ruby>えてくれると\\n<ruby><rb>信</rb><rt>しん</rt></ruby>じての<ruby><rb>誘</rb><rt>さそ</rt></ruby>いです。いかがですか？",
        "zh_cn": "我相信你一定不会辜负我的期待\\n才邀请你的。你意下如何？",
        "zh_tw": "因為我相信如果是你的話\\n一定能回應我的期待。如何呢？"
      },
      "voice": "",
      "book": ""
    },
    {
      "icon": "100019_02",
      "name": {
        "en_us": "Harle",
        "ja_jp": "ハール",
        "zh_cn": "哈尔",
        "zh_tw": "哈魯"
      },
      "context": {
        "en_us": "......",
        "ja_jp": "…………。",
        "zh_cn": "……",
        "zh_tw": "…………"
      },
      "voice": "",
      "book": ""
    },
    {
      "icon": "100019_02",
      "name": {
        "en_us": "Harle",
        "ja_jp": "ハール",
        "zh_cn": "哈尔",
        "zh_tw": "哈魯"
      },
      "context": {
        "en_us": "(It sounds too good to be true, but this is\\nundoubtedly a tremendous opportunity.)",
        "ja_jp": "（<ruby><rb>話</rb><rt>はなし</rt></ruby>が<ruby><rb>不自然</rb><rt>ふしぜん</rt></ruby>なほどに<ruby><rb>美味</rb><rt>うま</rt></ruby>すぎる。\\n　だが、これは<ruby><rb>間違</rb><rt>まちが</rt></ruby>いなく<ruby><rb>好機</rb><rt>こうき</rt></ruby>……！）",
        "zh_cn": "（天上哪会掉馅饼。\\n不过这也确实是一个\\n不可多得的机会！）",
        "zh_tw": "（這個提議理想到不自然的地步。\\n但是，的確是個好機會……！）"
      },
      "voice": "",
      "book": ""
    },
    {
      "icon": "100019_02",
      "name": {
        "en_us": "Harle",
        "ja_jp": "ハール",
        "zh_cn": "哈尔",
        "zh_tw": "哈魯"
      },
      "context": {
        "en_us": "(I may not know what His Highness's\\ntrue intentions are, but I will use him\\nin kind.)",
        "ja_jp": "（<ruby><rb>殿下</rb><rt>でんか</rt></ruby>の<ruby><rb>真意</rb><rt>しんい</rt></ruby>はわからないが、\\n　こちらも<ruby><rb>利用</rb><rt>りよう</rt></ruby>させてもらうまで）",
        "zh_cn": "（虽然不知道殿下是何用意，\\n但我又何尝不可利用他呢。）",
        "zh_tw": "（雖然不曉得殿下的真實意圖為何，\\n但我也只要加以利用就好。）"
      },
      "voice": "",
      "book": ""
    },
    {
      "icon": "100019_02",
      "name": {
        "en_us": "Harle",
        "ja_jp": "ハール",
        "zh_cn": "哈尔",
        "zh_tw": "哈魯"
      },
      "context": {
        "en_us": "I would be a fool to turn down such a\\nprivilege. I am yours to command, sir.",
        "ja_jp": "ファルエス<ruby><rb>様</rb><rt>さま</rt></ruby>のありがたいお<ruby><rb>誘</rb><rt>さそ</rt></ruby>いを\\nどうして<ruby><rb>断</rb><rt>ことわ</rt></ruby>れましょうか。\\n<ruby><rb>此度</rb><rt>こたび</rt></ruby>のお<ruby><rb>話</rb><rt>はなし</rt></ruby>、<ruby><rb>謹</rb><rt>つつし</rt></ruby>んでお<ruby><rb>受</rb><rt>う</rt></ruby>けいたします。",
        "zh_cn": "既然是法尔艾斯大人的美意，\\n我又怎么会拒绝呢。\\n恭敬不如从命。",
        "zh_tw": "法魯艾斯大人如此光榮的提議，\\n我如何能夠拒絕呢？\\n這次的提議，我非常樂意接受。"
      },
      "voice": "",
      "book": ""
    },
    {
      "icon": "100019_02",
      "name": {
        "en_us": "Harle",
        "ja_jp": "ハール",
        "zh_cn": "哈尔",
        "zh_tw": "哈魯"
      },
      "context": {
        "en_us": "After you, Your Highness.",
        "ja_jp": "ファルエス<ruby><rb>様</rb><rt>さま</rt></ruby>、どうぞ。",
        "zh_cn": "法尔艾斯大人，请。",
        "zh_tw": "法魯艾斯大人，請。"
      },
      "voice": "",
      "book": ""
    },
    {
      "icon": "100014_02",
      "name": {
        "en_us": "Phares",
        "ja_jp": "ファルエス",
        "zh_cn": "法尔艾斯",
        "zh_tw": "法魯艾斯"
      },
      "context": {
        "en_us": "Thank you for your hard work, and for seeing\\nme home to my research lab. I feel more at \\nease here than in the castle.",
        "ja_jp": "ええ。<ruby><rb>護衛</rb><rt>ごえい</rt></ruby>、ご<ruby><rb>苦労様</rb><rt>くろうさま</rt></ruby>です。\\nやはり<ruby><rb>城</rb><rt>しろ</rt></ruby>より<ruby><rb>研究所</rb><rt>けんきゅうじょ</rt></ruby>が<ruby><rb>落</rb><rt>お</rt></ruby>ち<ruby><rb>着</rb><rt>つ</rt></ruby>きますね。",
        "zh_cn": "嗯，辛苦你这一路的护送。\\n研究所果然比城堡\\n让人感到更自在啊。",
        "zh_tw": "嗯。護衛辛苦你了。\\n果然比起城裡，\\n還是研究所更讓人放鬆呢。"
      },
      "voice": "",
      "book": ""
    },
    {
      "icon": "100019_02",
      "name": {
        "en_us": "Harle",
        "ja_jp": "ハール",
        "zh_cn": "哈尔",
        "zh_tw": "哈魯"
      },
      "context": {
        "en_us": "I would never have guessed that this place\\nhoused a laboratory.",
        "ja_jp": "まさかこのような<ruby><rb>民家</rb><rt>みんか</rt></ruby>を<ruby><rb>研究所</rb><rt>けんきゅうじょ</rt></ruby>に\\nされているとは<ruby><rb>思</rb><rt>おも</rt></ruby>いませんでした。",
        "zh_cn": "没想到您竟然会把民宅\\n改造成研究所。",
        "zh_tw": "真沒想到您會以這般民宅當作研究所。"
      },
      "voice": "",
      "book": ""
    },
    {
      "icon": "100014_02",
      "name": {
        "en_us": "Phares",
        "ja_jp": "ファルエス",
        "zh_cn": "法尔艾斯",
        "zh_tw": "法魯艾斯"
      },
      "context": {
        "en_us": "Leif said the same thing.",
        "ja_jp": "ふふ、リーフも<ruby><rb>最初</rb><rt>さいしょ</rt></ruby>は\\n<ruby><rb>同</rb><rt>おな</rt></ruby>じことを<ruby><rb>言</rb><rt>い</rt></ruby>っていましたね。",
        "zh_cn": "呵呵，利弗一开始\\n也说过同样的话。",
        "zh_tw": "呵呵，李弗最初也跟你\\n說過一樣的話呢。"
      },
      "voice": "",
      "book": ""
    },
    {
      "icon": "100019_02",
      "name": {
        "en_us": "Harle",
        "ja_jp": "ハール",
        "zh_cn": "哈尔",
        "zh_tw": "哈魯"
      },
      "context": {
        "en_us": "Did he, now?",
        "ja_jp": "リーフも？",
        "zh_cn": "他也来过？",
        "zh_tw": "李弗也是？"
      },
      "voice": "",
      "book": ""
    },
    {
      "icon": "100014_02",
      "name": {
        "en_us": "Phares",
        "ja_jp": "ファルエス",
        "zh_cn": "法尔艾斯",
        "zh_tw": "法魯艾斯"
      },
      "context": {
        "en_us": "Indeed. In the past, I would occasionally\\nask him to go on errands for me. The man\\nis dependable to a fault, really.",
        "ja_jp": "ええ。たまにおつかいを<ruby><rb>手伝</rb><rt>てつだ</rt></ruby>って\\nもらっていました。\\n<ruby><rb>彼</rb><rt>かれ</rt></ruby>にはつい<ruby><rb>頼</rb><rt>たよ</rt></ruby>ってしまうんですよね。",
        "zh_cn": "是啊，我偶尔会让他帮我跑个腿。\\n他总是让人下意识地想依赖呢。",
        "zh_tw": "嗯。我偶爾會拜託他跑個腿。\\n總是會忍不住依賴他呢。"
      },
      "voice": "",
      "book": ""
    },
    {
      "icon": "100014_02",
      "name": {
        "en_us": "Phares",
        "ja_jp": "ファルエス",
        "zh_cn": "法尔艾斯",
        "zh_tw": "法魯艾斯"
      },
      "context": {
        "en_us": "His family has served mine for\\ngenerations, so we go back quite\\na ways.",
        "ja_jp": "<ruby><rb>代々</rb><rt>だいだい</rt></ruby><ruby><rb>王家</rb><rt>おうけ</rt></ruby>に<ruby><rb>仕</rb><rt>つか</rt></ruby>える<ruby><rb>家</rb><rt>いえ</rt></ruby>の<ruby><rb>出</rb><rt>で</rt></ruby>というのも\\nあって、<ruby><rb>彼</rb><rt>かれ</rt></ruby>とは<ruby><rb>私</rb><rt>わたし</rt></ruby>が<ruby><rb>幼</rb><rt>おさな</rt></ruby>い<ruby><rb>頃</rb><rt>ころ</rt></ruby>からの\\n<ruby><rb>付</rb><rt>つ</rt></ruby>き<ruby><rb>合</rb><rt>あ</rt></ruby>いなのですよ。",
        "zh_cn": "他出身于代代侍奉王室的世家，\\n我和他小时候就认识了。",
        "zh_tw": "因為他來自代代侍奉王家的家系，\\n所以我們從小就認識了。"
      },
      "voice": "",
      "book": ""
    },
    {
      "icon": "100014_02",
      "name": {
        "en_us": "Phares",
        "ja_jp": "ファルエス",
        "zh_cn": "法尔艾斯",
        "zh_tw": "法魯艾斯"
      },
      "context": {
        "en_us": "Incidentally, I'd been meaning to ask...\\nWhat were you doing before you\\njoined the Officers Academy?",
        "ja_jp": "<ruby><rb>幼</rb><rt>おさな</rt></ruby>い<ruby><rb>頃</rb><rt>ころ</rt></ruby>といえば……あなたは\\n<ruby><rb>将士</rb><rt>しょうし</rt></ruby><ruby><rb>学校</rb><rt>がっこう</rt></ruby>に<ruby><rb>入</rb><rt>はい</rt></ruby>るまでは<ruby><rb>何</rb><rt>なに</rt></ruby>を？",
        "zh_cn": "说到小时候……\\n你进入军事学校之前\\n是怎么生活的？",
        "zh_tw": "說到小時候……\\n你在進軍官學校前是做什麼的呢？"
      },
      "voice": "",
      "book": ""
    },
    {
      "icon": "100019_02",
      "name": {
        "en_us": "Harle",
        "ja_jp": "ハール",
        "zh_cn": "哈尔",
        "zh_tw": "哈魯"
      },
      "context": {
        "en_us": "I was a meager servant for a nobleman.",
        "ja_jp": "<ruby><rb>貴族</rb><rt>きぞく</rt></ruby>に<ruby><rb>雇</rb><rt>やと</rt></ruby>われていた<ruby><rb>底辺</rb><rt>ていへん</rt></ruby>の<ruby><rb>使用人</rb><rt>しようにん</rt></ruby>\\nでしたよ。",
        "zh_cn": "不过是受雇于贵族的\\n底层佣人罢了。",
        "zh_tw": "是個受僱於貴族的底層傭人。"
      },
      "voice": "",
      "book": ""
    },
    {
      "icon": "100014_02",
      "name": {
        "en_us": "Phares",
        "ja_jp": "ファルエス",
        "zh_cn": "法尔艾斯",
        "zh_tw": "法魯艾斯"
      },
      "context": {
        "en_us": "Interesting. What made you aspire to\\nknighthood?",
        "ja_jp": "もともと<ruby><rb>使用人</rb><rt>しようにん</rt></ruby>だったとは<ruby><rb>意外</rb><rt>いがい</rt></ruby>ですね。\\nどうして<ruby><rb>騎士</rb><rt>きし</rt></ruby>に？",
        "zh_cn": "没想到你以前是个佣人啊。\\n那你为什么成了骑士呢？",
        "zh_tw": "你原本是傭人這點真令我意外呢。\\n為什麼會想成為騎士？"
      },
      "voice": "",
      "book": ""
    },
    {
      "icon": "100019_02",
      "name": {
        "en_us": "Harle",
        "ja_jp": "ハール",
        "zh_cn": "哈尔",
        "zh_tw": "哈魯"
      },
      "context": {
        "en_us": "My master at the time was the picture of\\nmagnanimity. He would make any number\\nof arrangements to see a young man's\\nfuture brighten.",
        "ja_jp": "<ruby><rb>当時</rb><rt>とうじ</rt></ruby>の<ruby><rb>主人</rb><rt>しゅじん</rt></ruby>が<ruby><rb>慈悲深</rb><rt>じひぶか</rt></ruby>い<ruby><rb>方</rb><rt>かた</rt></ruby>でして。\\n<ruby><rb>少年</rb><rt>しょうねん</rt></ruby>の<ruby><rb>未来</rb><rt>みらい</rt></ruby>を<ruby><rb>拓</rb><rt>ひら</rt></ruby>こうと、いろいろと\\n<ruby><rb>便宜</rb><rt>べんぎ</rt></ruby>をはかってくださったのですよ。",
        "zh_cn": "我当时的雇主是个非常善良的人，\\n试图为少年开辟一条道路，\\n所以为我行了不少方便。",
        "zh_tw": "當時的主人相當仁慈。\\n說是為了開拓少年的未來，\\n而給了我許多特別待遇。"
      },
      "voice": "",
      "book": ""
    },
    {
      "icon": "100014_02",
      "name": {
        "en_us": "Phares",
        "ja_jp": "ファルエス",
        "zh_cn": "法尔艾斯",
        "zh_tw": "法魯艾斯"
      },
      "context": {
        "en_us": "You certainly lucked out, didn't you?\\nStill, I must caution you against lying.",
        "ja_jp": "それは<ruby><rb>幸運</rb><rt>こううん</rt></ruby>でしたね。\\nですが、<ruby><rb>嘘</rb><rt>うそ</rt></ruby>はよろしくないのでは？",
        "zh_cn": "那你可真是幸运。\\n不过，撒谎是不是不太好呢？",
        "zh_tw": "那還真是幸運呢。\\n不過，撒謊應該不好吧？"
      },
      "voice": "",
      "book": ""
    },
    {
      "icon": "100019_02",
      "name": {
        "en_us": "Harle",
        "ja_jp": "ハール",
        "zh_cn": "哈尔",
        "zh_tw": "哈魯"
      },
      "context": {
        "en_us": "I beg your pardon? I do not recall\\nspinning any falsehoods, Your Highness.",
        "ja_jp": "<ruby><rb>嘘</rb><rt>うそ</rt></ruby>……？　はて、<ruby><rb>何</rb><rt>なん</rt></ruby>のことだか\\n<ruby><rb>私</rb><rt>わたし</rt></ruby>にはさっぱり……。",
        "zh_cn": "撒谎？我不懂\\n您在说什么……",
        "zh_tw": "撒謊……？\\n您是指什麼呢，我完全不明白……"
      },
      "voice": "",
      "book": ""
    },
    {
      "icon": "100014_02",
      "name": {
        "en_us": "Phares",
        "ja_jp": "ファルエス",
        "zh_cn": "法尔艾斯",
        "zh_tw": "法魯艾斯"
      },
      "context": {
        "en_us": "A few years ago, a nobleman was exiled\\nafter committing an unspeakable crime.",
        "ja_jp": "<ruby><rb>数年</rb><rt>すうねん</rt></ruby><ruby><rb>前</rb><rt>まえ</rt></ruby>、とある<ruby><rb>貴族</rb><rt>きぞく</rt></ruby>が<ruby><rb>不正</rb><rt>ふせい</rt></ruby>を\\n<ruby><rb>犯</rb><rt>おか</rt></ruby>したために<ruby><rb>領地</rb><rt>りょうち</rt></ruby>を<ruby><rb>追</rb><rt>お</rt></ruby>われた<ruby><rb>事件</rb><rt>じけん</rt></ruby>が\\nありました。",
        "zh_cn": "几年前，发生了一件事——\\n有一个贵族因为犯下罪行\\n而被逐出了领地。",
        "zh_tw": "數年前，曾發生某位貴族因犯下罪行\\n而被逐出領地的事件。"
      },
      "voice": "",
      "book": ""
    },
    {
      "icon": "100019_02",
      "name": {
        "en_us": "Harle",
        "ja_jp": "ハール",
        "zh_cn": "哈尔",
        "zh_tw": "哈魯"
      },
      "context": {
        "en_us": "It sounds like a most terrible incident.\\nAnd yet I fail to see what it has to do\\nwith present conversation, sir.",
        "ja_jp": "そのような<ruby><rb>事件</rb><rt>じけん</rt></ruby>が……。ですが、\\nそれと<ruby><rb>私</rb><rt>わたし</rt></ruby>とどのような<ruby><rb>関係</rb><rt>かんけい</rt></ruby>が？",
        "zh_cn": "还有这种事……可是，\\n这和我有什么关系吗？",
        "zh_tw": "原來發生過那種事……不過，\\n和我又有什麼關係？"
      },
      "voice": "",
      "book": ""
    },
    {
      "icon": "100014_02",
      "name": {
        "en_us": "Phares",
        "ja_jp": "ファルエス",
        "zh_cn": "法尔艾斯",
        "zh_tw": "法魯艾斯"
      },
      "context": {
        "en_us": "Funny you should ask. It happened around\\nthe same time you attained knighthood.",
        "ja_jp": "ええ、ちょうど<ruby><rb>同</rb><rt>おな</rt></ruby>じ<ruby><rb>時期</rb><rt>じき</rt></ruby>でしたよね？\\nあなたが<ruby><rb>騎士</rb><rt>きし</rt></ruby>の<ruby><rb>身分</rb><rt>みぶん</rt></ruby>を<ruby><rb>手</rb><rt>て</rt></ruby>に<ruby><rb>入</rb><rt>い</rt></ruby>れたのと。",
        "zh_cn": "当然。这件事和你获得骑士身份\\n恰好发生在同一时期吧？",
        "zh_tw": "嗯，正好是差不多的時期吧？\\n和你得到騎士身分時。"
      },
      "voice": "",
      "book": ""
    },
    {
      "icon": "100014_02",
      "name": {
        "en_us": "Phares",
        "ja_jp": "ファルエス",
        "zh_cn": "法尔艾斯",
        "zh_tw": "法魯艾斯"
      },
      "context": {
        "en_us": "Surely a man of your intellect is aware\\nthat if servant were to, say, report his\\nmaster's crimes to the crown, he would\\nbe duly rewarded.",
        "ja_jp": "たとえば……<ruby><rb>使用人</rb><rt>しようにん</rt></ruby>が<ruby><rb>主人</rb><rt>しゅじん</rt></ruby>の<ruby><rb>不正</rb><rt>ふせい</rt></ruby>を\\n<ruby><rb>告発</rb><rt>こくはつ</rt></ruby>した、となれば……<ruby><rb>告発</rb><rt>こくはつ</rt></ruby>した<ruby><rb>者</rb><rt>もの</rt></ruby>は\\n<ruby><rb>相応</rb><rt>そうおう</rt></ruby>の<ruby><rb>褒美</rb><rt>ほうび</rt></ruby>を<ruby><rb>与</rb><rt>あた</rt></ruby>えられたでしょうね。",
        "zh_cn": "假设……佣人告发了雇主的恶行……\\n那么告发者应该会获得\\n相应的报酬吧。",
        "zh_tw": "比方說……假設傭人舉發了\\n主人的罪行，這樣一來……\\n舉發者想必能得到相應的獎賞吧。"
      },
      "voice": "",
      "book": ""
    },
    {
      "icon": "100019_02",
      "name": {
        "en_us": "Harle",
        "ja_jp": "ハール",
        "zh_cn": "哈尔",
        "zh_tw": "哈魯"
      },
      "context": {
        "en_us": "And you believe I would do such a thing?\\nYou jest. Why, that would be uncivilized.",
        "ja_jp": "それが<ruby><rb>私</rb><rt>わたし</rt></ruby>だと？　ご<ruby><rb>冗談</rb><rt>じょうだん</rt></ruby>を。\\n<ruby><rb>主人</rb><rt>しゅじん</rt></ruby>を<ruby><rb>踏</rb><rt>ふ</rt></ruby>み<ruby><rb>台</rb><rt>だい</rt></ruby>になんて、\\n<ruby><rb>恐</rb><rt>おそ</rt></ruby>れ<ruby><rb>多</rb><rt>おお</rt></ruby>くてできませんよ。",
        "zh_cn": "您想说那个人就是我？真会开玩笑。\\n把雇主当作垫脚石\\n这种冒犯之事我怎么敢做。",
        "zh_tw": "您認為那是我做的？真愛開玩笑。\\n將主人當作墊腳石這種事太可怕，\\n我可辦不到。"
      },
      "voice": "",
      "book": ""
    },
    {
      "icon": "100014_02",
      "name": {
        "en_us": "Phares",
        "ja_jp": "ファルエス",
        "zh_cn": "法尔艾斯",
        "zh_tw": "法魯艾斯"
      },
      "context": {
        "en_us": "Ah. My apologies, then. However, an\\ninteresting story does spring to mind.\\nPerhaps you've heard it.",
        "ja_jp": "それは<ruby><rb>失礼</rb><rt>しつれい</rt></ruby>しました。\\nでは、この<ruby><rb>話</rb><rt>はなし</rt></ruby>に<ruby><rb>覚</rb><rt>おぼ</rt></ruby>えは？",
        "zh_cn": "是我唐突了。\\n那这件事你还记得吗？",
        "zh_tw": "真是失禮了。\\n那麼，你對這件事有印象嗎？"
      },
      "voice": "",
      "book": ""
    },
    {
      "icon": "100014_02",
      "name": {
        "en_us": "Phares",
        "ja_jp": "ファルエス",
        "zh_cn": "法尔艾斯",
        "zh_tw": "法魯艾斯"
      },
      "context": {
        "en_us": "Not long ago, a messenger arrived from\\nGrams for a...secret rendezvous, we'll say.",
        "ja_jp": "<ruby><rb>先日</rb><rt>せんじつ</rt></ruby>グラムスの<ruby><rb>使者</rb><rt>ししゃ</rt></ruby>が<ruby><rb>訪</rb><rt>おとず</rt></ruby>れた<ruby><rb>際</rb><rt>さい</rt></ruby>、\\n<ruby><rb>彼</rb><rt>かれ</rt></ruby>に<ruby><rb>密会</rb><rt>みっかい</rt></ruby>した<ruby><rb>者</rb><rt>もの</rt></ruby>がいたようです。",
        "zh_cn": "前几天格拉姆斯的使者到访之际，\\n似乎有人与其私会。",
        "zh_tw": "前陣子葛拉姆斯的使者來訪時，\\n聽說曾有人與其私下會面。"
      },
      "voice": "",
      "book": ""
    },
    {
      "icon": "100014_02",
      "name": {
        "en_us": "Phares",
        "ja_jp": "ファルエス",
        "zh_cn": "法尔艾斯",
        "zh_tw": "法魯艾斯"
      },
      "context": {
        "en_us": "And who was their contact? My sources\\ndescribed him as a knight clad in black.\\nWhy, that sounds just like you.",
        "ja_jp": "その<ruby><rb>者</rb><rt>もの</rt></ruby>は<ruby><rb>黒</rb><rt>くろ</rt></ruby>い<ruby><rb>衣服</rb><rt>いふく</rt></ruby>の<ruby><rb>騎士</rb><rt>きし</rt></ruby>だったとか。\\nああ、ちょうどあなたのような。",
        "zh_cn": "听说那个人是一位\\n身穿黑色衣服的骑士，\\n哎呀，正好和你穿的这身差不多。",
        "zh_tw": "還聽說那個人是位身著黑服的騎士。\\n啊啊，正巧就像你一樣。"
      },
      "voice": "",
      "book": ""
    },
    {
      "icon": "100019_02",
      "name": {
        "en_us": "Harle",
        "ja_jp": "ハール",
        "zh_cn": "哈尔",
        "zh_tw": "哈魯"
      },
      "context": {
        "en_us": "Heavens! What a misunderstanding this is.\\nI did indeed meet with the messenger in\\nquestion, but I was simply showing him\\naround the capital. I AM chief of its guard.",
        "ja_jp": "<ruby><rb>誤解</rb><rt>ごかい</rt></ruby>です。たしかに<ruby><rb>私</rb><rt>わたし</rt></ruby>は<ruby><rb>使者殿</rb><rt>ししゃどの</rt></ruby>に\\nお<ruby><rb>会</rb><rt>あ</rt></ruby>いしましたが、<ruby><rb>王都</rb><rt>おうと</rt></ruby><ruby><rb>守備</rb><rt>しゅび</rt></ruby><ruby><rb>隊</rb><rt>たい</rt></ruby>として\\n<ruby><rb>王都</rb><rt>おうと</rt></ruby>をご<ruby><rb>案内</rb><rt>あんない</rt></ruby>していたにすぎません。",
        "zh_cn": "您误会了。我确实与使者见过面，\\n但只是代表王都守卫队\\n为其介绍王都而已。",
        "zh_tw": "您誤會了。我確實見過使者閣下，\\n但只是以王都守衛隊的身分，\\n為其導覽王都而已。"
      },
      "voice": "",
      "book": ""
    },
    {
      "icon": "100014_02",
      "name": {
        "en_us": "Phares",
        "ja_jp": "ファルエス",
        "zh_cn": "法尔艾斯",
        "zh_tw": "法魯艾斯"
      },
      "context": {
        "en_us": "Oh, is that all? Here I was certain\\nyou were sharing intelligence.",
        "ja_jp": "おや、そうでしたか。\\n<ruby><rb>私</rb><rt>わたし</rt></ruby>はてっきり<ruby><rb>情報交換</rb><rt>じょうほうこうかん</rt></ruby>でも\\nしていたのかと<ruby><rb>思</rb><rt>おも</rt></ruby>いましたよ。",
        "zh_cn": "哎呀，原来是这样啊。\\n我还以为你们一定\\n是在交换情报呢。",
        "zh_tw": "哎呀，原來是這樣。\\n我還以為一定是在進行\\n什麼情報交換呢。"
      },
      "voice": "",
      "book": ""
    },
    {
      "icon": "100019_02",
      "name": {
        "en_us": "Harle",
        "ja_jp": "ハール",
        "zh_cn": "哈尔",
        "zh_tw": "哈魯"
      },
      "context": {
        "en_us": "......",
        "ja_jp": "…………。",
        "zh_cn": "……",
        "zh_tw": "…………"
      },
      "voice": "",
      "book": ""
    },
    {
      "icon": "100014_02",
      "name": {
        "en_us": "Phares",
        "ja_jp": "ファルエス",
        "zh_cn": "法尔艾斯",
        "zh_tw": "法魯艾斯"
      },
      "context": {
        "en_us": "You wish to create a world where all\\nhuman beings stand shoulder to\\nshoulder as equals.",
        "ja_jp": "あなたはすべての<ruby><rb>人間</rb><rt>にんげん</rt></ruby>が<ruby><rb>平等</rb><rt>びょうどう</rt></ruby>に\\n<ruby><rb>評価</rb><rt>ひょうか</rt></ruby>される<ruby><rb>世界</rb><rt>せかい</rt></ruby>を<ruby><rb>目指</rb><rt>めざ</rt></ruby>している。",
        "zh_cn": "我知道你希望创造一个\\n人人都能得到公正评价的世界。",
        "zh_tw": "你的目標是所有人都能\\n平等獲得評價的世界。"
      },
      "voice": "",
      "book": ""
    },
    {
      "icon": "100014_02",
      "name": {
        "en_us": "Phares",
        "ja_jp": "ファルエス",
        "zh_cn": "法尔艾斯",
        "zh_tw": "法魯艾斯"
      },
      "context": {
        "en_us": "But such a thing is impossible in a\\nkingdom with a class system. Therefore...",
        "ja_jp": "しかし、<ruby><rb>身分</rb><rt>みぶん</rt></ruby><ruby><rb>制</rb><rt>せい</rt></ruby>が<ruby><rb>存在</rb><rt>そんざい</rt></ruby>する<ruby><rb>今</rb><rt>いま</rt></ruby>の<ruby><rb>王国</rb><rt>おうこく</rt></ruby>では\\nそれは<ruby><rb>叶</rb><rt>かな</rt></ruby>わない……だとしたら――",
        "zh_cn": "但是，这个王国的身份制度\\n阻碍了你……既然如此——",
        "zh_tw": "然而，在這個存在身分制度的王國\\n無法實現那個理想……這麼一來──"
      },
      "voice": "",
      "book": ""
    },
    {
      "icon": "100014_02",
      "name": {
        "en_us": "Phares",
        "ja_jp": "ファルエス",
        "zh_cn": "法尔艾斯",
        "zh_tw": "法魯艾斯"
      },
      "context": {
        "en_us": "It would only be natural for you to devise\\na plan to destroy this kingdom and build\\none that suits your ideals upon its ashes.",
        "ja_jp": "<ruby><rb>一度</rb><rt>いちど</rt></ruby><ruby><rb>壊</rb><rt>こわ</rt></ruby>して<ruby><rb>理想</rb><rt>りそう</rt></ruby>の<ruby><rb>国家</rb><rt>こっか</rt></ruby>を<ruby><rb>打</rb><rt>う</rt></ruby>ち<ruby><rb>立</rb><rt>た</rt></ruby>てる……\\nそのような<ruby><rb>計画</rb><rt>けいかく</rt></ruby>を<ruby><rb>立</rb><rt>た</rt></ruby>てていても\\n<ruby><rb>不自然</rb><rt>ふしぜん</rt></ruby>ではありませんよね？",
        "zh_cn": "毁灭这个王国之后建立理想国度……\\n你会有这种计划也不足为奇吧？",
        "zh_tw": "先將其破壞再重新打造理想的國家……\\n即使你擬訂了這樣的計畫，\\n也是很自然的對吧？"
      },
      "voice": "",
      "book": ""
    },
    {
      "icon": "100019_02",
      "name": {
        "en_us": "Harle",
        "ja_jp": "ハール",
        "zh_cn": "哈尔",
        "zh_tw": "哈魯"
      },
      "context": {
        "en_us": "You certainly live up to your reputation\\nas an esteemed researcher, my liege.\\nThat is quite the theory you have crafted.",
        "ja_jp": "さすが<ruby><rb>研究者</rb><rt>けんきゅうしゃ</rt></ruby>としても<ruby><rb>名高</rb><rt>なだか</rt></ruby>い\\nファルエス<ruby><rb>殿下</rb><rt>でんか</rt></ruby>。<ruby><rb>面白</rb><rt>おもしろ</rt></ruby>い<ruby><rb>仮説</rb><rt>かせつ</rt></ruby>です。",
        "zh_cn": "法尔艾斯殿下不愧是\\n大名鼎鼎的研究者，\\n这真是个有趣的假设。",
        "zh_tw": "法魯艾斯殿下不愧是知名的研究者。\\n非常有趣的假設。"
      },
      "voice": "",
      "book": ""
    },
    {
      "icon": "100019_02",
      "name": {
        "en_us": "Harle",
        "ja_jp": "ハール",
        "zh_cn": "哈尔",
        "zh_tw": "哈魯"
      },
      "context": {
        "en_us": "But I'm afraid a theory is all it is. My\\nloyalty lies with the Kingdom of Alberia.",
        "ja_jp": "ですが、<ruby><rb>仮説</rb><rt>かせつ</rt></ruby>は<ruby><rb>仮説</rb><rt>かせつ</rt></ruby>。<ruby><rb>私</rb><rt>わたし</rt></ruby>の<ruby><rb>忠義</rb><rt>ちゅうぎ</rt></ruby>は\\n<ruby><rb>今</rb><rt>いま</rt></ruby>もアルベリアに<ruby><rb>捧</rb><rt>ささ</rt></ruby>げております。",
        "zh_cn": "不过，只是假设罢了。我的忠诚\\n依旧献予阿尔贝里亚。",
        "zh_tw": "不過，假設只是假設。\\n我的忠義現在也屬於阿爾貝利亞。"
      },
      "voice": "",
      "book": ""
    },
    {
      "icon": "100014_02",
      "name": {
        "en_us": "Phares",
        "ja_jp": "ファルエス",
        "zh_cn": "法尔艾斯",
        "zh_tw": "法魯艾斯"
      },
      "context": {
        "en_us": "I see. Forgive me—I've always been\\nprone to overthinking. Terrible habit.",
        "ja_jp": "ふふ、そうでしたね。つい<ruby><rb>考</rb><rt>かんが</rt></ruby>えすぎて\\nしまうのが<ruby><rb>私</rb><rt>わたし</rt></ruby>の<ruby><rb>悪</rb><rt>わる</rt></ruby>い<ruby><rb>癖</rb><rt>くせ</rt></ruby>で。",
        "zh_cn": "呵呵，也是呢。\\n我这个人的毛病\\n就是总爱胡思乱想。",
        "zh_tw": "呵呵，你說得對。\\n一不小心就會考慮太多，\\n是我的壞習慣。"
      },
      "voice": "",
      "book": ""
    },
    {
      "icon": "100014_02",
      "name": {
        "en_us": "Phares",
        "ja_jp": "ファルエス",
        "zh_cn": "法尔艾斯",
        "zh_tw": "法魯艾斯"
      },
      "context": {
        "en_us": "Now, I must concentrate on my research,\\nso please stand by outside for me.",
        "ja_jp": "そろそろ<ruby><rb>研究</rb><rt>けんきゅう</rt></ruby>に<ruby><rb>集中</rb><rt>しゅうちゅう</rt></ruby>しますので、\\n<ruby><rb>外</rb><rt>そと</rt></ruby>で<ruby><rb>待機</rb><rt>たいき</rt></ruby>していてください。",
        "zh_cn": "我该集中精力做研究了，\\n你就在外面待命吧。",
        "zh_tw": "我差不多想專心研究了，\\n請你到外面等候吧。"
      },
      "voice": "",
      "book": ""
    },
    {
      "icon": "100019_02",
      "name": {
        "en_us": "Harle",
        "ja_jp": "ハール",
        "zh_cn": "哈尔",
        "zh_tw": "哈魯"
      },
      "context": {
        "en_us": "Your wish is my command.",
        "ja_jp": "ええ、<ruby><rb>承知</rb><rt>しょうち</rt></ruby>しました。",
        "zh_cn": "好的，遵命。",
        "zh_tw": "好的，遵命。"
      },
      "voice": "",
      "book": ""
    },
    {
      "icon": "100019_02",
      "name": {
        "en_us": "Harle",
        "ja_jp": "ハール",
        "zh_cn": "哈尔",
        "zh_tw": "哈魯"
      },
      "context": {
        "en_us": "(How much does that man know?!\\nAnd if he already pieced all that\\ntogether, then why did he take me\\non as his personal guard?)",
        "ja_jp": "（あの<ruby><rb>男</rb><rt>おとこ</rt></ruby>は、どこまで<ruby><rb>気</rb><rt>き</rt></ruby>づいて……。\\n　いや、あそこまで<ruby><rb>気</rb><rt>き</rt></ruby>づいていながら\\n　<ruby><rb>私</rb><rt>わたし</rt></ruby>を<ruby><rb>傍</rb><rt>そば</rt></ruby>に<ruby><rb>置</rb><rt>お</rt></ruby>く<ruby><rb>理由</rb><rt>りゆう</rt></ruby>は……？）",
        "zh_cn": "（那个男人到底了解多少……\\n不对，既然他知道了那么多，\\n为什么还把我放在身边？）",
        "zh_tw": "（那個男人，究竟知道多少……\\n不，既然知道了這麼多，\\n為什麼還將我放在身邊……？）"
      },
      "voice": "",
      "book": ""
    },
    {
      "icon": "100019_02",
      "name": {
        "en_us": "Harle",
        "ja_jp": "ハール",
        "zh_cn": "哈尔",
        "zh_tw": "哈魯"
      },
      "context": {
        "en_us": "Heh. I think I shall do a little bit of\\nresearch of my own, Prince Phares.",
        "ja_jp": "……<ruby><rb>私</rb><rt>わたし</rt></ruby>も<ruby><rb>調</rb><rt>しら</rt></ruby>べさせてもらいますよ、\\nファルエス<ruby><rb>殿下</rb><rt>でんか</rt></ruby>。",
        "zh_cn": "请恕我也要对您\\n进行一番调查了……\\n法尔艾斯殿下。",
        "zh_tw": "……我也會私下進行調查的，\\n法魯艾斯殿下。"
      },
      "voice": "",
      "book": ""
    },
    {
      "icon": "100019_02",
      "name": {
        "en_us": "Harle",
        "ja_jp": "ハール",
        "zh_cn": "哈尔",
        "zh_tw": "哈魯"
      },
      "context": {
        "en_us": "Now, if I were looking for information of\\nany importance, it would be right...here.",
        "ja_jp": "……まあ、<ruby><rb>目</rb><rt>め</rt></ruby>ぼしい<ruby><rb>情報</rb><rt>じょうほう</rt></ruby>があるとしたら\\nここになりますよね。",
        "zh_cn": "要说有价值的情报，\\n也只能在这里找了。",
        "zh_tw": "……嗯，若說會有什麼\\n有用情報的地方，大概就是這裡了吧。"
      },
      "voice": "",
      "book": ""
    },
    {
      "icon": "100019_02",
      "name": {
        "en_us": "Harle",
        "ja_jp": "ハール",
        "zh_cn": "哈尔",
        "zh_tw": "哈魯"
      },
      "context": {
        "en_us": "There's got to be something useful... Hm...\\nWhat do we have here—an old research\\npaper?",
        "ja_jp": "<ruby><rb>何</rb><rt>なに</rt></ruby>か<ruby><rb>得</rb><rt>え</rt></ruby>られればいいのですが……ん？\\nこれは……<ruby><rb>古</rb><rt>ふる</rt></ruby>い<ruby><rb>研究書</rb><rt>けんきゅうしょ</rt></ruby>？",
        "zh_cn": "希望有所收获……嗯？\\n这是……古老的研究书籍？",
        "zh_tw": "希望能有所收穫就好了……嗯？\\n這是……古老的研究書？"
      },
      "voice": "",
      "book": ""
    },
    {
      "icon": "100019_02",
      "name": {
        "en_us": "Harle",
        "ja_jp": "ハール",
        "zh_cn": "哈尔",
        "zh_tw": "哈魯"
      },
      "context": {
        "en_us": "The Progenitor... Demons... So he's not\\nyour everyday research scientist after all.\\nAnd there's another book shoved into the\\nback of the shelf...",
        "ja_jp": "……『はじまりの<ruby><rb>人</rb><rt>ひと</rt></ruby>』、『<ruby><rb>悪魔</rb><rt>あくま</rt></ruby>』……\\nこのような<ruby><rb>研究</rb><rt>けんきゅう</rt></ruby>もされていたのですね。\\nおや、<ruby><rb>棚</rb><rt>たな</rt></ruby>の<ruby><rb>裏</rb><rt>うら</rt></ruby>にもう<ruby><rb>一冊</rb><rt>いっさつ</rt></ruby>。",
        "zh_cn": "“起始之人”，“恶魔”……\\n原来他还研究这种东西啊。\\n咦，书架后面还有一本。",
        "zh_tw": "……「起始之人」、「惡魔」……\\n原來他也在研究這種事呢。\\n喔，櫃子後方還有一本。"
      },
      "voice": "",
      "book": ""
    },
    {
      "icon": "100019_02",
      "name": {
        "en_us": "Harle",
        "ja_jp": "ハール",
        "zh_cn": "哈尔",
        "zh_tw": "哈魯"
      },
      "context": {
        "en_us": "A child's handwriting, no doubt. It seems\\nto be a journal he kept as a child.",
        "ja_jp": "<ruby><rb>筆跡</rb><rt>ひっせき</rt></ruby>が<ruby><rb>幼</rb><rt>おさな</rt></ruby>い……<ruby><rb>子供</rb><rt>こども</rt></ruby>の<ruby><rb>頃</rb><rt>ころ</rt></ruby>の<ruby><rb>日誌</rb><rt>にっし</rt></ruby>の\\nようですね。",
        "zh_cn": "笔迹好稚嫩……\\n看起来是小时候写的日记。",
        "zh_tw": "筆跡相當幼稚……\\n看來是小時候的日誌。"
      },
      "voice": "",
      "book": ""
    },
    {
      "icon": "100019_02",
      "name": {
        "en_us": "Harle",
        "ja_jp": "ハール",
        "zh_cn": "哈尔",
        "zh_tw": "哈魯"
      },
      "context": {
        "en_us": "＂Day 13, Month of the Lovely Dragon:\\nIt appears this will be my final entry.＂",
        "ja_jp": "「<ruby><rb>麗竜</rb><rt>れいりゅう</rt></ruby>の<ruby><rb>月</rb><rt>つき</rt></ruby>　13<ruby><rb>日</rb><rt>にち</rt></ruby>\\n　これが<ruby><rb>最後</rb><rt>さいご</rt></ruby>の<ruby><rb>日誌</rb><rt>にっし</rt></ruby>になりそうだ――」",
        "zh_cn": "“丽龙之月　13日 \\n这似乎会成为最后的日记……”",
        "zh_tw": "「麗龍之月　13日\\n　看來這會成為最後一篇日誌──」"
      },
      "voice": "",
      "book": ""
    },
    {
      "icon": "100019_02",
      "name": {
        "en_us": "Harle",
        "ja_jp": "ハール",
        "zh_cn": "哈尔",
        "zh_tw": "哈魯"
      },
      "context": {
        "en_us": "＂My disease continues to plague me.\\nI suffer from a kind of sensory paralysis.\\nI lack all strength. My pulse slows.\\nMy hands are ice. My mind is in disarray.＂",
        "ja_jp": "「<ruby><rb>体</rb><rt>からだ</rt></ruby>の<ruby><rb>感覚</rb><rt>かんかく</rt></ruby>が<ruby><rb>麻痺</rb><rt>まひ</rt></ruby>している。\\n　<ruby><rb>力</rb><rt>ちから</rt></ruby>が<ruby><rb>入</rb><rt>はい</rt></ruby>らない。<ruby><rb>脈</rb><rt>みゃく</rt></ruby>も<ruby><rb>弱</rb><rt>よわ</rt></ruby>い。\\n　<ruby><rb>頭</rb><rt>あたま</rt></ruby>の<ruby><rb>中</rb><rt>なか</rt></ruby>が――ぐちゃぐちゃだ。」",
        "zh_cn": "“身体已经没有知觉。\\n使不上力气。脉搏也很微弱。\\n脑袋里一片混沌。”",
        "zh_tw": "「身體的知覺已經麻痺了。\\n　無法施力。脈膊也很微弱。\\n　腦中──一片混亂。」"
      },
      "voice": "",
      "book": ""
    },
    {
      "icon": "100019_02",
      "name": {
        "en_us": "Harle",
        "ja_jp": "ハール",
        "zh_cn": "哈尔",
        "zh_tw": "哈魯"
      },
      "context": {
        "en_us": "Odd. There's no record of the Prince's\\ncondition progressing this far in the\\nroyal archives.",
        "ja_jp": "……おかしいですね。<ruby><rb>殿下</rb><rt>でんか</rt></ruby>がここまで\\n<ruby><rb>竜鱗病</rb><rt>りゅうりんびょう</rt></ruby>に<ruby><rb>侵</rb><rt>おか</rt></ruby>されていた<ruby><rb>記録</rb><rt>きろく</rt></ruby>は\\n<ruby><rb>城</rb><rt>しろ</rt></ruby>の<ruby><rb>書庫</rb><rt>しょこ</rt></ruby>にはなかった。",
        "zh_cn": "怪了……城堡的书库里\\n并没有殿下被龙鳞病\\n如此折磨的记录。",
        "zh_tw": "……真是奇怪。城裡的書庫中並沒有\\n關於殿下的龍鱗病如此嚴重的記載。"
      },
      "voice": "",
      "book": ""
    },
    {
      "icon": "100019_02",
      "name": {
        "en_us": "Harle",
        "ja_jp": "ハール",
        "zh_cn": "哈尔",
        "zh_tw": "哈魯"
      },
      "context": {
        "en_us": "＂Day 14, Month of the Lovely Dragon:\\nI am alive! New strength courses\\nthrough my body.＂",
        "ja_jp": "「<ruby><rb>麗竜</rb><rt>れいりゅう</rt></ruby>の<ruby><rb>月</rb><rt>つき</rt></ruby>　14<ruby><rb>日</rb><rt>にち</rt></ruby>\\n　<ruby><rb>生</rb><rt>い</rt></ruby>きている――。<ruby><rb>体</rb><rt>からだ</rt></ruby>に<ruby><rb>新</rb><rt>あたら</rt></ruby>しい<ruby><rb>力</rb><rt>ちから</rt></ruby>が\\n　<ruby><rb>流</rb><rt>なが</rt></ruby>れ<ruby><rb>込</rb><rt>こ</rt></ruby>んでくるようだ」",
        "zh_cn": "“丽龙之月　14日\\n我还活着……\\n体内似乎正涌入一股新的力量。”",
        "zh_tw": "「麗龍之月　14日\\n　我還活著──\\n　感覺像有新的力量流進身體裡。」"
      },
      "voice": "",
      "book": ""
    },
    {
      "icon": "100019_02",
      "name": {
        "en_us": "Harle",
        "ja_jp": "ハール",
        "zh_cn": "哈尔",
        "zh_tw": "哈魯"
      },
      "context": {
        "en_us": "He recovered in a single day? Wait... No.\\nIf that previous paper is to be believed...",
        "ja_jp": "わずか1<ruby><rb>日</rb><rt>にち</rt></ruby>で<ruby><rb>快復</rb><rt>かいふく</rt></ruby>を？　いや、<ruby><rb>待</rb><rt>ま</rt></ruby>て。\\n<ruby><rb>先</rb><rt>さき</rt></ruby>ほどの<ruby><rb>研究書</rb><rt>けんきゅうしょ</rt></ruby>……！",
        "zh_cn": "仅仅一天就康复了？\\n不，等一下。\\n刚才的研究书籍……",
        "zh_tw": "僅用一天就康復了？不，等等。\\n剛才的研究書……！"
      },
      "voice": "",
      "book": ""
    },
    {
      "icon": "100019_02",
      "name": {
        "en_us": "Harle",
        "ja_jp": "ハール",
        "zh_cn": "哈尔",
        "zh_tw": "哈魯"
      },
      "context": {
        "en_us": "The Progenitor... Reincarnation...\\nVessels... An undying body...\\nIt can't be!",
        "ja_jp": "はじまりの<ruby><rb>人</rb><rt>ひと</rt></ruby>、<ruby><rb>転生</rb><rt>てんせい</rt></ruby>、<ruby><rb>器</rb><rt>うつわ</rt></ruby>、\\n<ruby><rb>死</rb><rt>し</rt></ruby>しても<ruby><rb>死</rb><rt>し</rt></ruby>なぬ<ruby><rb>肉体</rb><rt>にくたい</rt></ruby>……まさか――",
        "zh_cn": "起始之人、转世、容器，\\n不会完全死去的肉体……\\n难道——",
        "zh_tw": "起始之人、轉生、容器、\\n縱使死亡也不會逝去的肉體……\\n難不成──"
      },
      "voice": "",
      "book": ""
    },
    {
      "icon": "100019_02",
      "name": {
        "en_us": "???",
        "ja_jp": "？？？",
        "zh_cn": "？？？",
        "zh_tw": "？？？"
      },
      "context": {
        "en_us": "Now this won't do. You should know\\nbetter than to barge into someone's\\nprivate study.",
        "ja_jp": "いけませんね。\\n<ruby><rb>勝手</rb><rt>かって</rt></ruby>に<ruby><rb>研究所</rb><rt>けんきゅうじょ</rt></ruby>を<ruby><rb>荒</rb><rt>あ</rt></ruby>らすなど。",
        "zh_cn": "这可不行啊。\\n怎么能擅自翻我的研究所呢。",
        "zh_tw": "這可不行喔。\\n竟然擅自翻找研究所。"
      },
      "voice": "",
      "book": ""
    },
    {
      "icon": "100019_02",
      "name": {
        "en_us": "Harle",
        "ja_jp": "ハール",
        "zh_cn": "哈尔",
        "zh_tw": "哈魯"
      },
      "context": {
        "en_us": "?!",
        "ja_jp": "ッ!?",
        "zh_cn": "！？",
        "zh_tw": "唔！？"
      },
      "voice": "",
      "book": ""
    },
    {
      "icon": "120044_01",
      "name": {
        "en_us": "Phares",
        "ja_jp": "ファルエス",
        "zh_cn": "法尔艾斯",
        "zh_tw": "法魯艾斯"
      },
      "context": {
        "en_us": "I did not peg you as the scholarly type.",
        "ja_jp": "あなたがここまで<ruby><rb>研究</rb><rt>けんきゅう</rt></ruby>に<ruby><rb>興味</rb><rt>きょうみ</rt></ruby>が\\nおありだとは<ruby><rb>思</rb><rt>おも</rt></ruby>いませんでしたよ。",
        "zh_cn": "没想到你竟对研究\\n如此感兴趣。",
        "zh_tw": "我沒想到你對研究這麼感興趣呢。"
      },
      "voice": "",
      "book": ""
    },
    {
      "icon": "100019_02",
      "name": {
        "en_us": "Harle",
        "ja_jp": "ハール",
        "zh_cn": "哈尔",
        "zh_tw": "哈魯"
      },
      "context": {
        "en_us": "Prince Phares... No, perhaps I should\\ncall you by the name of the entity living\\nwithin you.",
        "ja_jp": "ファルエス<ruby><rb>殿下</rb><rt>でんか</rt></ruby>……いえ、<ruby><rb>貴方</rb><rt>あなた</rt></ruby>の<ruby><rb>中身</rb><rt>なかみ</rt></ruby>の\\n<ruby><rb>名</rb><rt>な</rt></ruby>でお<ruby><rb>呼</rb><rt>よ</rt></ruby>びした<ruby><rb>方</rb><rt>ほう</rt></ruby>がよろしいですか？",
        "zh_cn": "法尔艾斯殿下……\\n不，我是不是以您体内之人的\\n姓名称呼您比较好？",
        "zh_tw": "法魯艾斯殿下……不，\\n應該以你內在的名字稱呼比較好嗎？"
      },
      "voice": "",
      "book": ""
    },
    {
      "icon": "100014_02",
      "name": {
        "en_us": "Phares",
        "ja_jp": "ファルエス",
        "zh_cn": "法尔艾斯",
        "zh_tw": "法魯艾斯"
      },
      "context": {
        "en_us": "I haven't the faintest idea what you mean.\\nMore importantly, I have somebody I'd like\\nyou to meet. Say hello.",
        "ja_jp": "ふふ……<ruby><rb>何</rb><rt>なん</rt></ruby>のことでしょう？\\nそんなことよりも、あなたに<ruby><rb>紹介</rb><rt>しょうかい</rt></ruby>\\nしたい<ruby><rb>方</rb><rt>かた</rt></ruby>がいるのです。ご<ruby><rb>挨拶</rb><rt>あいさつ</rt></ruby>を。",
        "zh_cn": "呵呵……你在说什么？\\n这事先放一边，我想向你\\n介绍一个人。打个招呼吧。",
        "zh_tw": "呵呵……你是指什麼呢？\\n話說回來，我想介紹一個人給你。\\n打聲招呼吧。"
      },
      "voice": "",
      "book": ""
    },
    {
      "icon": "100019_01",
      "name": {
        "en_us": "???",
        "ja_jp": "？？？",
        "zh_cn": "？？？",
        "zh_tw": "？？？"
      },
      "context": {
        "en_us": "A pleasure to meet you at last.\\nFrom now on, I will be known as Harle.",
        "ja_jp": "はじめまして。\\n<ruby><rb>只今</rb><rt>ただいま</rt></ruby>より、<ruby><rb>私</rb><rt>わたし</rt></ruby>が『ハール』です。",
        "zh_cn": "初次见面。\\n从现在开始，我就是“哈尔”了。",
        "zh_tw": "初次見面。\\n從現在起，我就是「哈魯」。"
      },
      "voice": "",
      "book": ""
    },
    {
      "icon": "100019_02",
      "name": {
        "en_us": "Harle",
        "ja_jp": "ハール",
        "zh_cn": "哈尔",
        "zh_tw": "哈魯"
      },
      "context": {
        "en_us": "Who the hell are you?!",
        "ja_jp": "なっ……<ruby><rb>貴様</rb><rt>きさま</rt></ruby>は<ruby><rb>誰</rb><rt>だれ</rt></ruby>だ!?",
        "zh_cn": "什么……你是谁！？",
        "zh_tw": "什……你是誰！？"
      },
      "voice": "",
      "book": ""
    },
    {
      "icon": "100014_02",
      "name": {
        "en_us": "Phares",
        "ja_jp": "ファルエス",
        "zh_cn": "法尔艾斯",
        "zh_tw": "法魯艾斯"
      },
      "context": {
        "en_us": "Did you not hear? His name is Harle.\\nOh, but there is no need to fret.",
        "ja_jp": "ですから、『ハール』ですよ？\\nああ、ご<ruby><rb>安心</rb><rt>あんしん</rt></ruby>ください。",
        "zh_cn": "不是说了嘛，他是“哈尔”。\\n哦，你放心。",
        "zh_tw": "剛才說過了，這位是「哈魯」啊？\\n啊啊，請放心。"
      },
      "voice": "",
      "book": ""
    },
    {
      "icon": "100014_02",
      "name": {
        "en_us": "Phares",
        "ja_jp": "ファルエス",
        "zh_cn": "法尔艾斯",
        "zh_tw": "法魯艾斯"
      },
      "context": {
        "en_us": "Ever since you became my guard, he has\\nbeen lurking in the shadows, peering at\\nyour memories.",
        "ja_jp": "あなたが<ruby><rb>私</rb><rt>わたし</rt></ruby>の<ruby><rb>近衛</rb><rt>このえ</rt></ruby>になってから、\\nこの<ruby><rb>者</rb><rt>もの</rt></ruby>は<ruby><rb>影</rb><rt>かげ</rt></ruby>からあなたの<ruby><rb>記憶</rb><rt>きおく</rt></ruby>を\\n<ruby><rb>盗</rb><rt>ぬす</rt></ruby>み<ruby><rb>見</rb><rt>み</rt></ruby>ていたのです。",
        "zh_cn": "自从你当了我的近卫之后，\\n他就一直在暗地里\\n偷窥着你的记忆。",
        "zh_tw": "自從你成為我的近衛之後，\\n這位就一直躲在暗處窺視你的記憶。"
      },
      "voice": "",
      "book": ""
    },
    {
      "icon": "100014_02",
      "name": {
        "en_us": "Phares",
        "ja_jp": "ファルエス",
        "zh_cn": "法尔艾斯",
        "zh_tw": "法魯艾斯"
      },
      "context": {
        "en_us": "I am certain he will be the perfect\\nreplacement for you.",
        "ja_jp": "きっと<ruby><rb>上手</rb><rt>うま</rt></ruby>くあなたに\\n<ruby><rb>成</rb><rt>な</rt></ruby>り<ruby><rb>代</rb><rt>か</rt></ruby>わってくれるでしょう。",
        "zh_cn": "他一定会完美取代\\n你的位置。",
        "zh_tw": "相信一定能完美地代替你吧。"
      },
      "voice": "",
      "book": ""
    },
    {
      "icon": "100019_02",
      "name": {
        "en_us": "Harle",
        "ja_jp": "ハール",
        "zh_cn": "哈尔",
        "zh_tw": "哈魯"
      },
      "context": {
        "en_us": "Now I understand. THIS was why you\\nwanted me at arm's length.",
        "ja_jp": "なるほど……これが<ruby><rb>貴方</rb><rt>あなた</rt></ruby>の\\n<ruby><rb>魂胆</rb><rt>こんたん</rt></ruby>だったというわけですか。",
        "zh_cn": "原来如此……\\n这就是您的目的所在吗。",
        "zh_tw": "原來如此……\\n這就是你的企圖嗎。"
      },
      "voice": "",
      "book": ""
    },
    {
      "icon": "100014_02",
      "name": {
        "en_us": "Phares",
        "ja_jp": "ファルエス",
        "zh_cn": "法尔艾斯",
        "zh_tw": "法魯艾斯"
      },
      "context": {
        "en_us": "Those twisted little ideas festering\\ninside you suited him quite well.",
        "ja_jp": "あなたの<ruby><rb>捻</rb><rt>ひね</rt></ruby>くれたところは、\\n『<ruby><rb>彼</rb><rt>かれ</rt></ruby>』にとても<ruby><rb>似</rb><rt>に</rt></ruby>ていましたから。",
        "zh_cn": "因为你那别扭的性格\\n和“他”非常相似。",
        "zh_tw": "因為你那性格扭曲的部分，\\n和「他」非常相似。"
      },
      "voice": "",
      "book": ""
    },
    {
      "icon": "100014_02",
      "name": {
        "en_us": "Phares",
        "ja_jp": "ファルエス",
        "zh_cn": "法尔艾斯",
        "zh_tw": "法魯艾斯"
      },
      "context": {
        "en_us": "We couldn't have asked for a better\\nperson's life to usurp.",
        "ja_jp": "<ruby><rb>成</rb><rt>な</rt></ruby>り<ruby><rb>代</rb><rt>か</rt></ruby>わる<ruby><rb>相手</rb><rt>あいて</rt></ruby>として\\n<ruby><rb>最適</rb><rt>さいてき</rt></ruby>だったのです。",
        "zh_cn": "所以是最适合\\n被取代的人选。",
        "zh_tw": "作為取而代之的對象，\\n再適合不過了。"
      },
      "voice": "",
      "book": ""
    },
    {
      "icon": "100010_901",
      "name": {
        "en_us": "Harle",
        "ja_jp": "ハール",
        "zh_cn": "哈尔",
        "zh_tw": "哈魯"
      },
      "context": {
        "en_us": "Well, what an honor that is.",
        "ja_jp": "それは<ruby><rb>光栄</rb><rt>こうえい</rt></ruby>なことで……。",
        "zh_cn": "这还真是荣幸之至……",
        "zh_tw": "那還真是光榮呢……"
      },
      "voice": "",
      "book": ""
    },
    {
      "icon": "100014_02",
      "name": {
        "en_us": "Phares",
        "ja_jp": "ファルエス",
        "zh_cn": "法尔艾斯",
        "zh_tw": "法魯艾斯"
      },
      "context": {
        "en_us": "Now. You're a smart man. I'm sure\\nyou know what must happen next.",
        "ja_jp": "さて……<ruby><rb>賢</rb><rt>かしこ</rt></ruby>いあなたならば、\\nもうおわかりですね？",
        "zh_cn": "好了……\\n聪明如你应该猜到了吧？",
        "zh_tw": "好了……聰明如你，\\n應該已經明白了吧？"
      },
      "voice": "",
      "book": ""
    },
    {
      "icon": "100014_02",
      "name": {
        "en_us": "Phares",
        "ja_jp": "ファルエス",
        "zh_cn": "法尔艾斯",
        "zh_tw": "法魯艾斯"
      },
      "context": {
        "en_us": "There cannot be two Harles in this world.",
        "ja_jp": "この<ruby><rb>世界</rb><rt>せかい</rt></ruby>に『ハール』は\\nふたりもいりません。",
        "zh_cn": "这个世界上\\n不需要两个“哈尔”。",
        "zh_tw": "這個世界不需要兩位「哈魯」。"
      },
      "voice": "",
      "book": ""
    },
    {
      "icon": "100019_02",
      "name": {
        "en_us": "Harle",
        "ja_jp": "ハール",
        "zh_cn": "哈尔",
        "zh_tw": "哈魯"
      },
      "context": {
        "en_us": "!",
        "ja_jp": "ッ……！",
        "zh_cn": "！",
        "zh_tw": "唔……！"
      },
      "voice": "",
      "book": ""
    },
    {
      "icon": "100019_01",
      "name": {
        "en_us": "???",
        "ja_jp": "？？？",
        "zh_cn": "？？？",
        "zh_tw": "？？？"
      },
      "context": {
        "en_us": "One moment. If you're just going to kill\\nhim, why don't you let me play with him\\ninstead?",
        "ja_jp": "お<ruby><rb>待</rb><rt>ま</rt></ruby>ちください。どうせ<ruby><rb>殺</rb><rt>ころ</rt></ruby>すなら、\\nその<ruby><rb>玩具</rb><rt>おもちゃ</rt></ruby>、<ruby><rb>私</rb><rt>わたし</rt></ruby>にくださいな？",
        "zh_cn": "等一下，与其杀了他，\\n不如把这个玩具给我吧？",
        "zh_tw": "請等一下。既然都要殺，\\n不如將那個玩具給我吧？"
      },
      "voice": "",
      "book": ""
    },
    {
      "icon": "100019_01",
      "name": {
        "en_us": "???",
        "ja_jp": "？？？",
        "zh_cn": "？？？",
        "zh_tw": "？？？"
      },
      "context": {
        "en_us": "I've seen into this man's memories.\\nHe is QUITE the idealist.",
        "ja_jp": "この<ruby><rb>男</rb><rt>おとこ</rt></ruby>、<ruby><rb>記憶</rb><rt>きおく</rt></ruby>を<ruby><rb>覗</rb><rt>のぞ</rt></ruby>いたところなかなかの\\n<ruby><rb>理想家</rb><rt>りそうか</rt></ruby>のようではないですか。",
        "zh_cn": "根据我窥探到的记忆来看，\\n这个男人似乎是一个\\n心怀壮志的理想家呢。",
        "zh_tw": "那個男人，窺看他的記憶時，\\n發現他似乎是位頗熱情的理想家。"
      },
      "voice": "",
      "book": ""
    },
    {
      "icon": "100019_01",
      "name": {
        "en_us": "???",
        "ja_jp": "？？？",
        "zh_cn": "？？？",
        "zh_tw": "？？？"
      },
      "context": {
        "en_us": "Wouldn't it be exciting to see him crushed\\nby the weight of his own foolish notions?",
        "ja_jp": "そんな<ruby><rb>彼</rb><rt>かれ</rt></ruby>が<ruby><rb>理想</rb><rt>りそう</rt></ruby>に<ruby><rb>絶望</rb><rt>ぜつぼう</rt></ruby>する<ruby><rb>姿</rb><rt>すがた</rt></ruby>は\\nゾクゾクすると<ruby><rb>思</rb><rt>おも</rt></ruby>いません？",
        "zh_cn": "不觉得他为理想而绝望的样子\\n会让人很兴奋吗？",
        "zh_tw": "想到他對理想絕望時的模樣，\\n不覺得讓人興奮得顫抖嗎？"
      },
      "voice": "",
      "book": ""
    },
    {
      "icon": "100014_02",
      "name": {
        "en_us": "Phares",
        "ja_jp": "ファルエス",
        "zh_cn": "法尔艾斯",
        "zh_tw": "法魯艾斯"
      },
      "context": {
        "en_us": "I've no particular interest in such a thing,\\nbut by all means, do as you see fit.",
        "ja_jp": "<ruby><rb>私</rb><rt>わたし</rt></ruby>は<ruby><rb>興味</rb><rt>きょうみ</rt></ruby>ありませんが、いいでしょう。\\n<ruby><rb>好</rb><rt>す</rt></ruby>きになさい。",
        "zh_cn": "我倒是不感兴趣，\\n不过就随你吧。",
        "zh_tw": "雖然我沒什麼興趣，不過好吧。\\n隨便你處置。"
      },
      "voice": "",
      "book": ""
    },
    {
      "icon": "100019_02",
      "name": {
        "en_us": "Harle",
        "ja_jp": "ハール",
        "zh_cn": "哈尔",
        "zh_tw": "哈魯"
      },
      "context": {
        "en_us": "What do you think you're—",
        "ja_jp": "<ruby><rb>何</rb><rt>なに</rt></ruby>を<ruby><rb>勝手</rb><rt>かって</rt></ruby>に……！",
        "zh_cn": "少自作主张！",
        "zh_tw": "竟然擅自……！"
      },
      "voice": "",
      "book": ""
    },
    {
      "icon": "100019_01",
      "name": {
        "en_us": "???",
        "ja_jp": "？？？",
        "zh_cn": "？？？",
        "zh_tw": "？？？"
      },
      "context": {
        "en_us": "No more struggling.\\nIt's time we said goodbye.",
        "ja_jp": "<ruby><rb>無駄</rb><rt>むだ</rt></ruby>ですよ。\\nさあ、お<ruby><rb>別</rb><rt>わか</rt></ruby>れの<ruby><rb>時間</rb><rt>じかん</rt></ruby>です。",
        "zh_cn": "别做无谓的抵抗了。\\n来吧，告别的时刻到了。",
        "zh_tw": "沒用的喔。\\n好了，該道別了。"
      },
      "voice": "",
      "book": ""
    },
    {
      "icon": "100019_02",
      "name": {
        "en_us": "Harle",
        "ja_jp": "ハール",
        "zh_cn": "哈尔",
        "zh_tw": "哈魯"
      },
      "context": {
        "en_us": "A tear in space?! Nngh... I'm...\\nI'm getting sucked in! AGH!",
        "ja_jp": "<ruby><rb>空間</rb><rt>くうかん</rt></ruby>が<ruby><rb>裂</rb><rt>さ</rt></ruby>けた!?\\nクッ……<ruby><rb>吸</rb><rt>す</rt></ruby>い<ruby><rb>込</rb><rt>こ</rt></ruby>まれる……ッ、\\nうわああああああ！",
        "zh_cn": "空间裂开了！？\\n呃……要被吸进去了……\\n哇啊啊啊啊啊啊！",
        "zh_tw": "空間裂開了！？\\n唔……要被吸進去……\\n嗚哇啊啊啊啊啊啊！"
      },
      "voice": "",
      "book": ""
    },
    {
      "icon": "100019_01",
      "name": {
        "en_us": "???",
        "ja_jp": "？？？",
        "zh_cn": "？？？",
        "zh_tw": "？？？"
      },
      "context": {
        "en_us": "Farewell, old Harle. Have yourself a\\nfun little sojourn in another world.",
        "ja_jp": "ごきげんよう、<ruby><rb>元</rb><rt>もと</rt></ruby>『ハール』。\\nどうぞ<ruby><rb>異界</rb><rt>いかい</rt></ruby>で<ruby><rb>愉快</rb><rt>ゆかい</rt></ruby>に<ruby><rb>踊</rb><rt>おど</rt></ruby>ってくださいね？",
        "zh_cn": "再见了，原来的“哈尔”。\\n请在异界愉快地起舞吧。",
        "zh_tw": "保重了，前「哈魯」。\\n請你在異界愉快地起舞吧？"
      },
      "voice": "",
      "book": ""
    },
    {
      "icon": "100019_02",
      "name": {
        "en_us": "Harle",
        "ja_jp": "ハール",
        "zh_cn": "哈尔",
        "zh_tw": "哈魯"
      },
      "context": {
        "en_us": "Ngh... Where is this? Am I...still alive?",
        "ja_jp": "うっ……ここは……？\\n<ruby><rb>私</rb><rt>わたし</rt></ruby>は、<ruby><rb>生</rb><rt>い</rt></ruby>きているのか……？",
        "zh_cn": "唔……这里是……\\n我……还活着吗？",
        "zh_tw": "唔……這裡是……？\\n我、還活著嗎……？"
      },
      "voice": "",
      "book": ""
    },
    {
      "icon": "100019_02",
      "name": {
        "en_us": "Harle",
        "ja_jp": "ハール",
        "zh_cn": "哈尔",
        "zh_tw": "哈魯"
      },
      "context": {
        "en_us": "What a desolate place...\\nWhere in the world did they dump me?",
        "ja_jp": "<ruby><rb>酷</rb><rt>ひど</rt></ruby>い<ruby><rb>荒地</rb><rt>あれち</rt></ruby>ですね……。\\n<ruby><rb>私</rb><rt>わたし</rt></ruby>はどこに<ruby><rb>捨</rb><rt>す</rt></ruby>てられて……ん？",
        "zh_cn": "真是一片荒芜啊……\\n我被扔到了哪里……嗯？",
        "zh_tw": "好淒涼的荒野……\\n我究竟被扔到了哪裡……嗯？"
      },
      "voice": "",
      "book": ""
    },
    {
      "icon": "100019_02",
      "name": {
        "en_us": "Harle",
        "ja_jp": "ハール",
        "zh_cn": "哈尔",
        "zh_tw": "哈魯"
      },
      "context": {
        "en_us": "That volcano... Am I in Valkaheim?",
        "ja_jp": "あの<ruby><rb>火山</rb><rt>かざん</rt></ruby>は……もしやバルカヘイム？",
        "zh_cn": "那座火山……\\n难道是巴尔加海姆？",
        "zh_tw": "那座火山……莫非是巴爾加海姆？"
      },
      "voice": "",
      "book": ""
    },
    {
      "icon": "100013_01",
      "name": {
        "en_us": "Leonidas",
        "ja_jp": "レオニード",
        "zh_cn": "莱昂尼多",
        "zh_tw": "雷歐尼特"
      },
      "context": {
        "en_us": "Heed me, my subjects! The Kingdom of\\nAlberia has at last been unified under\\nthe eldest of its royals, Leonidas!",
        "ja_jp": "<ruby><rb>皆</rb><rt>みな</rt></ruby>の<ruby><rb>者</rb><rt>もの</rt></ruby>、<ruby><rb>聞</rb><rt>き</rt></ruby>け！　アルベリア<ruby><rb>王国</rb><rt>おうこく</rt></ruby>は\\n<ruby><rb>王家</rb><rt>おうけ</rt></ruby>の<ruby><rb>長子</rb><rt>ちょうし</rt></ruby>、レオニードが<ruby><rb>統一</rb><rt>とういつ</rt></ruby>した！",
        "zh_cn": "众人听令！阿尔贝里亚王国\\n由王室的长子——\\n莱昂尼多统一了！",
        "zh_tw": "眾人聽好！\\n阿爾貝利亞王國已由王家長子──\\n雷歐尼特統一了！"
      },
      "voice": "",
      "book": ""
    },
    {
      "icon": "120108_01",
      "name": {
        "en_us": "Crowd",
        "ja_jp": "民衆",
        "zh_cn": "民众",
        "zh_tw": "民眾"
      },
      "context": {
        "en_us": "Hail our unity! Hail King Leonidas!",
        "ja_jp": "<ruby><rb>統一</rb><rt>とういつ</rt></ruby><ruby><rb>万歳</rb><rt>ばんざい</rt></ruby>！　レオニード<ruby><rb>様</rb><rt>さま</rt></ruby><ruby><rb>万歳</rb><rt>ばんざい</rt></ruby>！",
        "zh_cn": "统一万岁！\\n莱昂尼多大人万岁！",
        "zh_tw": "統一萬歲！雷歐尼特大人萬歲！"
      },
      "voice": "",
      "book": ""
    },
    {
      "icon": "100019_02",
      "name": {
        "en_us": "Harle",
        "ja_jp": "ハール",
        "zh_cn": "哈尔",
        "zh_tw": "哈魯"
      },
      "context": {
        "en_us": "(Prince Leonidas did what? Nonsense.\\nI've never heard anything about this.)",
        "ja_jp": "（レオニード<ruby><rb>様</rb><rt>さま</rt></ruby>による<ruby><rb>王国</rb><rt>おうこく</rt></ruby>の<ruby><rb>統一</rb><rt>とういつ</rt></ruby>……？\\n　なんだそれは……そんな<ruby><rb>話</rb><rt>はなし</rt></ruby>、\\n　<ruby><rb>聞</rb><rt>き</rt></ruby>いていないぞ）",
        "zh_cn": "（莱昂尼多大人统一了王国？\\n这是怎么回事……\\n我怎么没听说。）",
        "zh_tw": "（雷歐尼特大人統一了王國……？\\n這是怎麼回事……\\n那種事，我可沒聽說啊。）"
      },
      "voice": "",
      "book": ""
    },
    {
      "icon": "100013_01",
      "name": {
        "en_us": "Leonidas",
        "ja_jp": "レオニード",
        "zh_cn": "莱昂尼多",
        "zh_tw": "雷歐尼特"
      },
      "context": {
        "en_us": "Listen well as we elucidate the new status\\nquo. Prime Minister, if you would?",
        "ja_jp": "これからのことは<ruby><rb>宰相</rb><rt>さいしょう</rt></ruby>より<ruby><rb>申</rb><rt>もう</rt></ruby>し<ruby><rb>伝</rb><rt>つた</rt></ruby>える。\\nあとは<ruby><rb>頼</rb><rt>たの</rt></ruby>んだぞ。",
        "zh_cn": "接下来的事就由宰相代为传达。\\n交给你了。",
        "zh_tw": "今後的事項由宰相向各位報告。\\n接下來拜託你了。"
      },
      "voice": "",
      "book": ""
    },
    {
      "icon": "100019_02",
      "name": {
        "en_us": "Harle",
        "ja_jp": "ハール",
        "zh_cn": "哈尔",
        "zh_tw": "哈魯"
      },
      "context": {
        "en_us": "(＂Prime Minister＂? Wait... Is that—?!)",
        "ja_jp": "（<ruby><rb>宰相</rb><rt>さいしょう</rt></ruby>？　なっ……！\\n　あれは……!?）",
        "zh_cn": "（宰相？什么！\\n那个人是……）",
        "zh_tw": "（宰相？什麼……！\\n那是……！？）"
      },
      "voice": "",
      "book": ""
    }
  ]
}