{
    "story_id": "",
    "story_icon": "",
    "outline": {
        "title": "",
        "content": [
            "要跳过此剧情吗？"
        ]
    },
    "story_content": [
        {
            "speaker_id": [],
            "speaker_name": "客人",
            "context": "服务员！点单！",
            "voice_line": "",
            "book_image": ""
        },
        {
            "speaker_id": [],
            "speaker_name": "天音",
            "context": "好，来了！",
            "voice_line": "",
            "book_image": ""
        },
        {
            "speaker_id": [],
            "speaker_name": "客人",
            "context": "服务员，\\n刚才点的菜怎么还没上啊？",
            "voice_line": "",
            "book_image": ""
        },
        {
            "speaker_id": [],
            "speaker_name": "天音",
            "context": "噢，请稍等一下！",
            "voice_line": "",
            "book_image": ""
        },
        {
            "speaker_id": [],
            "speaker_name": "客人",
            "context": "服务员！",
            "voice_line": "",
            "book_image": ""
        },
        {
            "speaker_id": [],
            "speaker_name": "天音",
            "context": "请、请等一下！",
            "voice_line": "",
            "book_image": ""
        },
        {
            "speaker_id": [],
            "speaker_name": "天音",
            "context": "哈啊、哈啊……\\n这客流量也太惊人了。\\n终于熬到休息时间了……",
            "voice_line": "",
            "book_image": ""
        },
        {
            "speaker_id": [],
            "speaker_name": "天音",
            "context": "自从在店里吹起了风，\\n“猫·海之家”的人气就持续飙升。\\n客流量也在不断增长……",
            "voice_line": "",
            "book_image": ""
        },
        {
            "speaker_id": [],
            "speaker_name": "天音",
            "context": "但今天也太多人了吧！？",
            "voice_line": "",
            "book_image": ""
        },
        {
            "speaker_id": [],
            "speaker_name": "妮娜",
            "context": "是啊……只靠我们两个\\n有点困难……要是因为我们\\n应付不过来而影响了店的名声……",
            "voice_line": "",
            "book_image": ""
        },
        {
            "speaker_id": [],
            "speaker_name": "天音",
            "context": "那、那可不行！\\n唔，就没有什么办法吗！？\\n真是连猫也想请来当外援！",
            "voice_line": "",
            "book_image": ""
        },
        {
            "speaker_id": [],
            "speaker_name": "埃利亚斯",
            "context": "你看起来很苦恼的样子，没事吧？",
            "voice_line": "",
            "book_image": ""
        },
        {
            "speaker_id": [],
            "speaker_name": "SYS",
            "context": "哈耳摩尼亚合唱团的少年\\n埃利亚斯",
            "voice_line": "",
            "book_image": ""
        },
        {
            "speaker_id": [],
            "speaker_name": "皮雅茜",
            "context": "哇，天音。你穿的那件\\n是海之家的制服吗？好可爱！",
            "voice_line": "",
            "book_image": ""
        },
        {
            "speaker_id": [],
            "speaker_name": "SYS",
            "context": "哈耳摩尼亚合唱团的少女\\n皮雅茜",
            "voice_line": "",
            "book_image": ""
        },
        {
            "speaker_id": [],
            "speaker_name": "天音",
            "context": "你们是……埃利亚斯和皮雅茜。\\n为什么会在这里！？",
            "voice_line": "",
            "book_image": ""
        },
        {
            "speaker_id": [],
            "speaker_name": "埃利亚斯",
            "context": "明天这附近有塞壬的演唱会，\\n我们是来听那个的。",
            "voice_line": "",
            "book_image": ""
        },
        {
            "speaker_id": [],
            "speaker_name": "皮雅茜",
            "context": "来了之后听说\\n天音在给海之家帮忙，\\n我们就来看你了！",
            "voice_line": "",
            "book_image": ""
        },
        {
            "speaker_id": [],
            "speaker_name": "埃利亚斯",
            "context": "不过情况看起来\\n比预想的还要棘手，\\n要不要我们也来帮忙？",
            "voice_line": "",
            "book_image": ""
        },
        {
            "speaker_id": [],
            "speaker_name": "天音",
            "context": "那真是求之不得。老板，\\n可以让他俩来帮忙吗？",
            "voice_line": "",
            "book_image": ""
        },
        {
            "speaker_id": [],
            "speaker_name": "妮娜",
            "context": "嗯，当然～那就拜托你\\n指导他们了，可以吗？",
            "voice_line": "",
            "book_image": ""
        },
        {
            "speaker_id": [],
            "speaker_name": "天音",
            "context": "嗯，那还用说。\\n都包在我身上了！",
            "voice_line": "",
            "book_image": ""
        },
        {
            "speaker_id": [],
            "speaker_name": "天音",
            "context": "就是这样，你俩听好了。\\n你们主要负责接单和上菜。",
            "voice_line": "",
            "book_image": ""
        },
        {
            "speaker_id": [],
            "speaker_name": "天音",
            "context": "有什么问题就叫我。\\n我马上帮你们解决！",
            "voice_line": "",
            "book_image": ""
        },
        {
            "speaker_id": [],
            "speaker_name": "皮雅茜",
            "context": "哇啊……\\n天音，真可靠啊！",
            "voice_line": "",
            "book_image": ""
        },
        {
            "speaker_id": [],
            "speaker_name": "天音",
            "context": "哼哼，我不仅是姐姐，\\n还是海之家的前辈呢！\\n埃利亚斯，对吧？",
            "voice_line": "",
            "book_image": ""
        },
        {
            "speaker_id": [],
            "speaker_name": "埃利亚斯",
            "context": "嗯。那就靠你了，前辈姐姐。\\n我这就去接单。",
            "voice_line": "",
            "book_image": ""
        },
        {
            "speaker_id": [],
            "speaker_name": "天音",
            "context": "嗯！要时刻牢记\\n给客人带来笑容！",
            "voice_line": "",
            "book_image": ""
        },
        {
            "speaker_id": [],
            "speaker_name": "天音",
            "context": "那么～我就趁这段时间\\n把餐具都摆好，\\n方便上菜吧……",
            "voice_line": "",
            "book_image": ""
        },
        {
            "speaker_id": [],
            "speaker_name": "皮雅茜",
            "context": "啊，天音！帮帮我！",
            "voice_line": "",
            "book_image": ""
        },
        {
            "speaker_id": [],
            "speaker_name": "天音",
            "context": "什么！？这就出问题了！？\\n我来了！",
            "voice_line": "",
            "book_image": ""
        },
        {
            "speaker_id": [],
            "speaker_name": "埃利亚斯",
            "context": "啊，天音！这位老爷爷\\n只肯点奇怪的菜品，\\n我该怎么办……",
            "voice_line": "",
            "book_image": ""
        },
        {
            "speaker_id": [],
            "speaker_name": "老爷爷",
            "context": "才不是奇怪的菜品！\\n是“回忆再现”啊！",
            "voice_line": "",
            "book_image": ""
        },
        {
            "speaker_id": [],
            "speaker_name": "皮雅茜",
            "context": "诶诶……我们都跟他说了\\n本店没有这道菜……",
            "voice_line": "",
            "book_image": ""
        },
        {
            "speaker_id": [],
            "speaker_name": "老爷爷",
            "context": "这怎么行！吃不到这个，\\n我不就白来海边了吗！",
            "voice_line": "",
            "book_image": ""
        },
        {
            "speaker_id": [],
            "speaker_name": "埃利亚斯",
            "context": "就是这么回事……要怎么办？\\n不知道他说的是什么，也没法做啊。\\n虽然有点对不住他，但只能请他回……",
            "voice_line": "",
            "book_image": ""
        },
        {
            "speaker_id": [],
            "speaker_name": "天音",
            "context": "不可以。这样的话，\\n就无法让这位老人露出笑容。",
            "voice_line": "",
            "book_image": ""
        },
        {
            "speaker_id": [],
            "speaker_name": "埃利亚斯",
            "context": "诶？可是……",
            "voice_line": "",
            "book_image": ""
        },
        {
            "speaker_id": [],
            "speaker_name": "天音",
            "context": "不明白的话，问清楚就好。\\n好在我是奇迹之神子，\\n最擅长的就是倾听别人的话语。",
            "voice_line": "",
            "book_image": ""
        },
        {
            "speaker_id": [],
            "speaker_name": "天音",
            "context": "这位老人，告诉我吧。那个……\\n“回忆再现”有什么特征吗？",
            "voice_line": "",
            "book_image": ""
        },
        {
            "speaker_id": [],
            "speaker_name": "老爷爷",
            "context": "啊～那是我年轻的时候\\n在这里的海之家吃到的\\n一道著名的荞麦面料理。",
            "voice_line": "",
            "book_image": ""
        },
        {
            "speaker_id": [],
            "speaker_name": "天音",
            "context": "噢噢，是荞麦面对吧？\\n是什么味道？什么颜色？",
            "voice_line": "",
            "book_image": ""
        },
        {
            "speaker_id": [],
            "speaker_name": "老爷爷",
            "context": "我记得是黄色的荞麦面上\\n浇着带有酸辣味的黑色酱汁。",
            "voice_line": "",
            "book_image": ""
        },
        {
            "speaker_id": [],
            "speaker_name": "天音",
            "context": "嗯嗯。除了酱汁呢？\\n还记得里面放了什么菜吗？",
            "voice_line": "",
            "book_image": ""
        },
        {
            "speaker_id": [],
            "speaker_name": "老爷爷",
            "context": "唔～有红的和绿的蔬菜……\\n噢对了，还有一块\\n美味至极的薄蛋卷！",
            "voice_line": "",
            "book_image": ""
        },
        {
            "speaker_id": [],
            "speaker_name": "天音",
            "context": "明白了，请您稍等。\\n埃利亚斯，皮雅茜，\\n你们两个跟我来。",
            "voice_line": "",
            "book_image": ""
        },
        {
            "speaker_id": [],
            "speaker_name": "皮雅茜",
            "context": "天音，你打算怎么办？",
            "voice_line": "",
            "book_image": ""
        },
        {
            "speaker_id": [],
            "speaker_name": "天音",
            "context": "那还用说嘛！\\n当然是要重现老人口中的\\n“回忆再现”啦！",
            "voice_line": "",
            "book_image": ""
        },
        {
            "speaker_id": [],
            "speaker_name": "天音",
            "context": "埃利亚斯，你负责面的焯水！\\n皮雅茜，蔬菜切好了吗？",
            "voice_line": "",
            "book_image": ""
        },
        {
            "speaker_id": [],
            "speaker_name": "皮雅茜",
            "context": "切、切好了。红色和绿色的蔬菜\\n都切成了能一口吃下去的大小！",
            "voice_line": "",
            "book_image": ""
        },
        {
            "speaker_id": [],
            "speaker_name": "埃利亚斯",
            "context": "我这边的面也煮好了！\\n接下来呢？",
            "voice_line": "",
            "book_image": ""
        },
        {
            "speaker_id": [],
            "speaker_name": "天音",
            "context": "嗯。接下来只要把拜托老板\\n准备的酱汁浇上去……\\n就完成了！我去上菜！",
            "voice_line": "",
            "book_image": ""
        },
        {
            "speaker_id": [],
            "speaker_name": "天音",
            "context": "这位老人，让您久等了！\\n这是您点的“回忆再现”！",
            "voice_line": "",
            "book_image": ""
        },
        {
            "speaker_id": [],
            "speaker_name": "老爷爷",
            "context": "我都等不及。那我就开动了。\\n啊呜……这、这是！",
            "voice_line": "",
            "book_image": ""
        },
        {
            "speaker_id": [],
            "speaker_name": "老爷爷",
            "context": "好怀念……不会错的，\\n这就是我回忆中的味道！",
            "voice_line": "",
            "book_image": ""
        },
        {
            "speaker_id": [],
            "speaker_name": "老爷爷",
            "context": "啊，回忆在脑海中苏醒……\\n真是名副其实的回忆再现啊！\\n筷子停不下来！",
            "voice_line": "",
            "book_image": ""
        },
        {
            "speaker_id": [],
            "speaker_name": "老爷爷",
            "context": "多谢款待！\\n谢谢你，小姑娘。\\n我很满意。来，给你钱。",
            "voice_line": "",
            "book_image": ""
        },
        {
            "speaker_id": [],
            "speaker_name": "天音",
            "context": "嗯！能让您满意，我也很高兴。\\n请慢走！",
            "voice_line": "",
            "book_image": ""
        },
        {
            "speaker_id": [],
            "speaker_name": "皮雅茜",
            "context": "哇……真是太厉害了！\\n天音竟然让那位顽固的老爷爷\\n也露出了笑容！",
            "voice_line": "",
            "book_image": ""
        },
        {
            "speaker_id": [],
            "speaker_name": "埃利亚斯",
            "context": "不过，你是怎么重现\\n老爷爷所说的料理的？",
            "voice_line": "",
            "book_image": ""
        },
        {
            "speaker_id": [],
            "speaker_name": "天音",
            "context": "那位老人不是说是荞麦面嘛。\\n于是我就想到了\\n日出之国的料理……",
            "voice_line": "",
            "book_image": ""
        },
        {
            "speaker_id": [],
            "speaker_name": "天音",
            "context": "因为我曾听居住在我国、和日出之国\\n有渊源的民众提到过一些料理，\\n所以就与其特征进行比对。",
            "voice_line": "",
            "book_image": ""
        },
        {
            "speaker_id": [],
            "speaker_name": "天音",
            "context": "我听过的话就不会忘。\\n不过，能顺利做出来真是太好了。",
            "voice_line": "",
            "book_image": ""
        },
        {
            "speaker_id": [],
            "speaker_name": "埃利亚斯",
            "context": "诶……你很厉害嘛，天音。",
            "voice_line": "",
            "book_image": ""
        },
        {
            "speaker_id": [],
            "speaker_name": "天音",
            "context": "哼哼。况且我在这间海之家\\n也在不断成长呢！",
            "voice_line": "",
            "book_image": ""
        },
        {
            "speaker_id": [],
            "speaker_name": "天音",
            "context": "如今，我能让所有客人\\n都露出笑容！\\n哼哼，你们就尊敬我吧！",
            "voice_line": "",
            "book_image": ""
        },
        {
            "speaker_id": [],
            "speaker_name": "皮雅茜",
            "context": "嗯！我非常尊敬天音哦！",
            "voice_line": "",
            "book_image": ""
        },
        {
            "speaker_id": [],
            "speaker_name": "埃利亚斯",
            "context": "啊哈哈。就这次来说，\\n也许真的可以尊敬……嗯？",
            "voice_line": "",
            "book_image": ""
        },
        {
            "speaker_id": [],
            "speaker_name": "皮雅茜",
            "context": "啊，好像又有客人来了！\\n欢迎光……",
            "voice_line": "",
            "book_image": ""
        },
        {
            "speaker_id": [],
            "speaker_name": "埃利亚斯",
            "context": "呃，是龙！？天音，没问题吗？\\n你应付得了龙吗？",
            "voice_line": "",
            "book_image": ""
        },
        {
            "speaker_id": [],
            "speaker_name": "天音",
            "context": "只要是不会危害人类的龙，\\n都应该平等相待。\\n我看看……",
            "voice_line": "",
            "book_image": ""
        },
        {
            "speaker_id": [],
            "speaker_name": "天音",
            "context": "啊！？",
            "voice_line": "",
            "book_image": ""
        },
        {
            "speaker_id": [],
            "speaker_name": "？？？",
            "context": "嘎嗷嗷嗷嗷嗷嗷嗷！",
            "voice_line": "",
            "book_image": ""
        },
        {
            "speaker_id": [],
            "speaker_name": "天音",
            "context": "啊……啊，啊啊啊！\\n给、给、给我回去！",
            "voice_line": "",
            "book_image": ""
        },
        {
            "speaker_id": [],
            "speaker_name": "埃尔默",
            "context": "唔！？看来我\\n不太受欢迎啊。",
            "voice_line": "",
            "book_image": ""
        },
        {
            "speaker_id": [],
            "speaker_name": "埃尔默",
            "context": "这家开在回忆之地的店风评很好，\\n我还想来品尝一下的……\\n没办法。告辞。",
            "voice_line": "",
            "book_image": ""
        },
        {
            "speaker_id": [],
            "speaker_name": "皮雅茜",
            "context": "呜呜……龙回去了！",
            "voice_line": "",
            "book_image": ""
        },
        {
            "speaker_id": [],
            "speaker_name": "天音",
            "context": "哈啊，哈啊……我、我究竟……\\n做了什么……",
            "voice_line": "",
            "book_image": ""
        },
        {
            "speaker_id": [],
            "speaker_name": "埃利亚斯",
            "context": "我才想问呢！\\n你怎么能用魔法\\n攻击客人呢！？",
            "voice_line": "",
            "book_image": ""
        },
        {
            "speaker_id": [],
            "speaker_name": "天音",
            "context": "太……太像了。",
            "voice_line": "",
            "book_image": ""
        },
        {
            "speaker_id": [],
            "speaker_name": "天音",
            "context": "他跟过去毁灭我故乡的龙\\n太像了。所以我的脑袋\\n变得一片空白……",
            "voice_line": "",
            "book_image": ""
        },
        {
            "speaker_id": [],
            "speaker_name": "埃利亚斯&皮雅茜",
            "context": "！",
            "voice_line": "",
            "book_image": ""
        },
        {
            "speaker_id": [],
            "speaker_name": "天音",
            "context": "不过，他已经不在这世上了！\\n今天那头龙是无辜的。\\n但我竟然把他赶跑了！",
            "voice_line": "",
            "book_image": ""
        },
        {
            "speaker_id": [],
            "speaker_name": "天音",
            "context": "我……我怎么会\\n做出这样的事……",
            "voice_line": "",
            "book_image": ""
        }
    ]
}